{
  "dataList": [
    {
      "id": 971042,
      "name": "",
      "desc": "ตอนนี้เราอยู่ที่จุดทางเข้าดันเจี้ยนแห่งห้วงหยั่งลึก\n\nเราพบว่า ตัวเองอยู่ในห้องที่เหมือนเวิร์คช็อปของอุปกรณ์ E.G.O\n\n'หยิบของขวัญ E.G.O จากตรงนี้ไปเพียงหนึ่งชิ้น หากคุณทำคะแนนอัตราซิงโครไนซ์ได้ต่ำกว่า 100% ในการทดสอบความสามารถ'\n\nมีป้ายเตือนน่ากลัวตั้งเตือนเราอยู่ และคำพูดนั้นก็ถูกย้ำผ่านลำโพงวิทยุไม่หยุดหย่อน\n\nเหล่าซินเนอร์ต่างเดินเข้าไปดู เพราะถูกชักจูงโดยป้ายที่บอกว่าเราหยิบอุปกรณ์ E.G.O ที่นี่ไปได้... แต่สิ่งที่เราพบกลับเป็นของขวัญ E.G.O\n\n\"หา? นี่มันไม่ใช่อุปกรณ์ E.G.O นี่หว่า พวกนี้... มันคือของขวัญอะไรนั่นใช่มะ?\"\n\n\"ดูเหมือน E.G.O ที่ปรากฏขึ้นที่นี่จะอยู่ในรูปลักษณ์ของของขวัญ E.G.O\"\n\n\"อืม เราเอาไปให้หมดเลยไม่ได้เหรอ?\"\n\n\"นี่คือดันเจี้ยนแห่งห้วงหยั่งลึกค่ะ เนื่องจากมันนั้นแตกต่างไปจากดันเจี้ยนปกติทั่วไป ขอแนะนำว่าให้ปฏิบัติตามกฎจะดีกว่านะคะ\"\n\nเราจะทำยังไงดี?",
      "options": [
        {
          "message": "หยิบถุงมือที่ไฟกำลังลุกอยู่",
          "messageDesc": "เลือกเพื่อรับของขวัญ E.G.O เผาไหม้ 1 ชิ้น",
          "result": [
            "เจ้านี่ดูจะเหมาะกับสถานการณ์ตอนนี้ที่สุดแล้ว\n\nเราหยิบของขวัญ E.G.O 'ถุงมือเผาไหม้' ออกมา"
          ]
        },
        {
          "message": "หยิบรองเท้าคอมแบตที่มีหนามติดอยู่บ้าง",
          "messageDesc": "เลือกเพื่อรับของขวัญ E.G.O ฉีกกระชาก 1 ชิ้น",
          "result": [
            "เจ้านี่ดูจะเหมาะกับสถานการณ์ตอนนี้ที่สุดแล้ว\n\nเราหยิบของขวัญ E.G.O 'รองเท้าคอมแบตติดหนาม' ออกมา"
          ]
        },
        {
          "message": "หยิบสเปรย์สารทำความสะอาดออกมา",
          "messageDesc": "เลือกเพื่อรับของขวัญ E.G.O ไร้หมวด 1 ชิ้น",
          "result": [
            "เจ้านี่ดูจะเหมาะกับสถานการณ์ตอนนี้ที่สุดแล้ว\n\nเราหยิบของขวัญ E.G.O 'การไล่ล่าลวงโลก' ออกมา"
          ]
        }
      ]
    },
    {
      "id": 971043,
      "name": "",
      "desc": "We came across a group of researchers passionately poring over various documents.\n\nThey're having a debate about two subjects: emotions and flame.\n\n\"Regular flames don't seem to hurt the Abnormalities very much. So why does this work, I wonder...?\"\n\n\"Perhaps a greater degree of wrathful emotions opens up the room for the fire's heat to touch Abnormalities and Distortions, both entities of the unknown.\"\n\nThey must've noticed us listening in to their conversation intently—one of them approaches us with a glint in their eyes.\n\n\"Are you the 'sample' who's agreed to this experiment?\"\n\n\"If so, try this on.\"\n\nIn the researcher's hands was what looked like an ignition plug... or a testing machine of sorts.",
      "options": [
        {
          "message": "You have the wrong person.",
          "messageDesc": "",
          "result": [
            "\"Wha? You're not the sample?\"\n\n\"Then what the hell are you doing in here? Get out, now!\"\n\nWe were kicked out."
          ]
        },
        {
          "message": "We're the 'samples'.",
          "messageDesc": "Run a Wrath & Lust Advantage check เพื่อรับของขวัญ E.G.O เผาไหม้ 1 ชิ้น",
          "result": [
            ""
          ]
        }
      ]
    },
    {
      "id": 971044,
      "name": "",
      "desc": "Several researchers are moving about busily in a hectic-looking laboratory.\n\nDid something escape, or something?\n\nAs we stood there gawking at the mess, someone walked up to the Sinners.\n\n\"Get outta my way!\"\n\n\"A-actually, you know what? Perfect timing.\"\n\n\"Eat this. C'mon, we don't have much time 'till the clinical trial report deadline!\"",
      "options": [
        {
          "message": "Eat it.",
          "messageDesc": "Run a Gluttony & Gloom Advantage check เพื่อรับของขวัญ E.G.O ฉีกกระชาก 1 ชิ้น",
          "result": [
            ""
          ]
        },
        {
          "message": "We're not eating that. We don't even know what that is.",
          "messageDesc": "",
          "result": [
            "\"Well, then get the hell outta my way!\"\n\nThe researcher pushed us aside."
          ]
        }
      ]
    },
    {
      "id": 971045,
      "name": "",
      "desc": "We see the Ardor Blossom Moth within the containment unit.\n\nSmall, crimson particles of flame surround it like an aura.\n\nThe flaming wings die out one moment, only to roar vigorously in the next.\n\nAn incessant attempt to set fire to everything around it.\n\n\"What a beautiful specimen, this Ardor Blossom Moth. Have you finished your observations?\"\n\n\"We've been learning a lot about the Abnormality recently.\"\n\n\"There's still a lot of unknowns, but still.\"\n\n\"Speaking of which, here's a pop quiz. What E.G.O Gift can you get from the Ardor Blossom Moth?\"",
      "options": [
        {
          "message": "ผลิบานใต้ผิวน้ำ",
          "messageDesc": "เลือกคำตอบที่ถูกต้อง เพื่อรับของขวัญ E.G.O เผาไหม้ 1 ชิ้น",
          "result": [
            "\"…….\"\n\n\"Pay more attention next time.\"\n\nThe researcher brushed past us."
          ]
        },
        {
          "message": "ฝันของผีเสื้อโลกันต์",
          "messageDesc": "เลือกคำตอบที่ถูกต้อง เพื่อรับของขวัญ E.G.O เผาไหม้ 1 ชิ้น",
          "result": [
            "\"Right on the money. You know your Ardor Blossom Moth.\"\n\n\"But that's not all. Recently, it's been giving out these things, too.\"\n\n\"Take this with you. I'm just glad to have run into a kindred soul.\"\n\nYou receive a burning, flickering flame. It seems to have come directly from the Ardor Blossom Moth itself."
          ]
        }
      ]
    },
    {
      "id": 971046,
      "name": "",
      "desc": "We see the Faelantern within the containment unit.\n\nA cyan-hued fairy flutters toward the wiry, ancient branches of the tree and softly lands on one of them.\n\nThe branch seating the fairy sways, as though to entice us to get closer to them...\n\nBright, countless yellow eyes glimmer from the shadows beneath its roots.\n\n\"What a beautiful specimen, this Faelantern. Have you finished your observations?\"\n\n\"We've been learning a lot about the Abnormality recently.\"\n\n\"There's still a lot of unknowns, but still.\"\n\n\"Speaking of which, here's a pop quiz. What E.G.O Gift can you get from the Faelantern?\"",
      "options": [
        {
          "message": "ฝันร้ายกลางเหมันต์",
          "messageDesc": "เลือกคำตอบที่ถูกต้อง เพื่อรับของขวัญ E.G.O ฉีกกระชาก 1 ชิ้น",
          "result": [
            "\"Right on the money. You know your Faelantern.\"\n\n\"But that's not all. Recently, it's been giving out these things, too.\"\n\n\"Take this with you. I'm just glad to have run into a kindred soul.\"\n\nYou receive a bony twig. It seems to have come directly from the Faelantern itself."
          ]
        },
        {
          "message": "โค้งเว้า",
          "messageDesc": "เลือกคำตอบที่ถูกต้อง เพื่อรับของขวัญ E.G.O ฉีกกระชาก 1 ชิ้น",
          "result": [
            "\"…….\"\n\n\"Pay more attention next time.\"\n\nThe researcher brushed past us."
          ]
        }
      ]
    },
    {
      "id": 971047,
      "name": "",
      "desc": "At the end of this hallway, a group of researchers is having a discussion in front of an unnaturally dark place.\n\nNoticing our presence, their faces brighten up as they approach us.\n\n\"Please, will you investigate this area ahead for us?\"\n\n\"We will help with the best of our abilities should you accept.\"",
      "options": [
        {
          "message": "Accept and investigate.",
          "messageDesc": "Heal all allies\nRun a Pride & Envy Advantage check เพื่อรับของขวัญ E.G.O ไร้หมวด 1 ชิ้น",
          "result": [
            ""
          ]
        },
        {
          "message": "Refuse.",
          "messageDesc": "",
          "result": [
            "\"Fine, walk away.\"\n\n\"We're not the ones losing out on a good deal.\"\n\nThe researchers all turned around without a moment's hesitation."
          ]
        }
      ]
    },
    {
      "id": 971048,
      "name": "",
      "desc": "Several messy, frantic letters are carved into the wall with knives.\n\nI can practically feel the sheer horror and desperation of their writers from the wild letters.\n\nUpon close inspection, the deep marks tell a tale written in terror.\n\n'They're swarming us the monsters I hear them their breathing they're going to kill us all'\n\n'Save me please someone anyone save me I dont want to die please'\n\n'Fear is what drives men to madness. The monsters are near, I can feel the rumble of their feet. They are coming…'\n\nThere are unfinished sentences written on the wall.\n\nDeath has carved deep marks between them.",
      "options": [
        {
          "message": "Ignore them and move on.",
          "messageDesc": "",
          "result": [
            "Nothing good can possibly come out of poking around in here. This won't be good for the Sinners.\n\nWe decided to quickly walk away from that place."
          ]
        },
        {
          "message": "Look around some more.",
          "messageDesc": "Run a Wrath & Gloom Advantage check เพื่อรับของขวัญ E.G.O ไร้หมวด 1 ชิ้น",
          "result": [
            ""
          ]
        }
      ]
    }
  ]
}