{
  "dataList": [
    {
      "id": 90145,
      "name": "ผู้โดยสารถุงโลหิตหิวกระหาย",
      "desc": "Core"
    },
    {
      "id": 90146,
      "name": "ผู้โดยสารถุงโลหิตผู้รุนแรง",
      "desc": "Core"
    },
    {
      "id": 90147,
      "name": "ผู้โดยสารถุงโลหิตผู้ดุร้าย",
      "desc": "Core"
    },
    {
      "id": 90148,
      "name": "พนักงานเก็บกวาดถุงโลหิตไร้ความปรานี",
      "desc": "Core"
    },
    {
      "id": 90149,
      "name": "พนักงานเก็บกวาดถุงโลหิตบ้าคลั่ง",
      "desc": "Core"
    },
    {
      "id": 90150,
      "name": "พนักงานเก็บกวาดถุงโลหิตหิวโซ",
      "desc": "Core"
    },
    {
      "id": 90151,
      "name": "ฟิกเซอร์อวัยวะเทียมถุงโลหิต",
      "desc": "Core"
    },
    {
      "id": 91018,
      "name": "ซาช่า",
      "desc": "Core"
    },
    {
      "id": 8350,
      "name": "คาสเซ็ตติ",
      "desc": "Core"
    },
    {
      "id": 835001,
      "name": "ลำตัว",
      "desc": "Core"
    }
  ]
}