{
  "dataList": [
    {
      "id": 139001,
      "name": "โปรดให้งานเทศกาลเลือดไหลเวียน",
      "desc": "การต่อสู้จะดำเนินไปสู่เฟสต่อไป เมื่อ 'ตุ๊กตาดินเผา' ทั้งหมดถูกกำจัด"
    },
    {
      "id": 139003,
      "name": "โปรดให้งานเทศกาลเพลิงลุกโชน",
      "desc": "หาก 'แขน' ทั้งสองข้างถูกทำลาย หรือหาก HP ของแกนหลักลดเหลือ 70% จะทำให้การต่อสู้ดำเนินการสู่ช่วงต่อไป"
    },
    {
      "id": 139004,
      "name": "ระห่ำดุเดือด",
      "desc": "ในการต่อสู้เฟสที่ 3: เมื่อเริ่มเทิร์น จะสร้างค่า [Combustion] 7 หน่วยแก่ศัตรูทั้งหมด"
    },
    {
      "id": 139006,
      "name": "โปรดให้งานเทศกาลดวงดาวร่วงโรย",
      "desc": "เมื่อ HP แกนหลักลดลงเหลือ 25% จะทำให้การต่อสู้ดำเนินการสู่ช่วงต่อไป"
    },
    {
      "id": 139101,
      "name": "บูชาไม่ลืมหูลืมตา",
      "desc": "ไม่ตายเมื่อมี HP 0 หน่วย; แต่จะอยู่บนสนามโดยไม่ขยับและไม่สามารถถูกเล็งได้แทน\n- จะถูกปราบปรามต่อเมื่อ 'ปฏิทินวันโลกาวินาศ' ถูกปราบปราม"
    },
    {
      "id": 139301,
      "name": "อดีตหวนคืน",
      "desc": "หากมี [AccumulatedPast] 50+ หน่วย และ HP ของแกนหลักนั้นเท่ากับ 80% หรือต่ำกว่า จะทำให้แกนหลักฟื้นฟู HP 200 หน่วยโดยการผลาญ [AccumulatedPast] 50 หน่วยเมื่อจบเทิร์น"
    },
    {
      "id": 139302,
      "name": "อดีตผิดที่ผิดทาง",
      "desc": "เมื่ออวัยวะ 'ลำตัว' ถูกทำลาย:\n- ผลาญ [AccumulatedPast] ทั้งหมด\n- นับแต่เทิร์นถัดไป ตัวคูณความต้านทานกายภาพและธาตุบาปของลำตัวจะกลายเป็น 'ทนมาก (x0.5)' จนกว่าจะจบการเผชิญหน้า"
    },
    {
      "id": 139303,
      "name": "ช่องไอเสียพังทลาย",
      "desc": "เมื่อ 'บลาสเตอร์ไอน้ำ' ถูกทำลาย จะเสีย [Breath] ทั้งหมดของอวัยวะทุกส่วน\n\nหลังจาก 'บลาสเตอร์ไอน้ำ' ถูกทำลาย\n- ได้รับ [Vulnerable] เท่ากับค่า [Breath] ทุกครั้งที่ตัวละครนี้ได้รับค่า [Breath]\n- เสียค่า [Breath] 1 หน่วย ทุกครั้งที่ตัวละครนี้ใช้สกิลโจมตี"
    },
    {
      "id": 139304,
      "name": "ไอน้ำรั่วไหล",
      "desc": "เมื่อ 'บลาสเตอร์ไอน้ำ' ถูกโจมตี จะเสียค่าและจำนวนครั้ง [Breath] อย่างละ 1 หน่วย"
    },
    {
      "id": 139305,
      "name": "เมโตรโนมจับจังหวะ",
      "desc": "หาก [AccumulatedPast]:\n- เป็นเลขคี่ จะได้รับ [Vulnerable] และ [AttackDmgUp] อย่างละ 3 หน่วย\n- เป็นเลขคู่ จะได้รับ [Protection] และ [AttackDmgDown] อย่างละ 3 หน่วย"
    },
    {
      "id": 139401,
      "name": "สัตว์ปีกฮึกเหิม",
      "desc": "จบเทิร์น: ฟื้นฟู HP 5 หน่วย ตามจำนวน 'ไก่ดิบ' ที่ยังอยู่บนการต่อสู้"
    },
    {
      "id": 139402,
      "name": "ไก่ป่าซึมทุกข์",
      "desc": "จบเทิร์น: สร้างความเสียหาย SP 5 หน่วยแก่ศัตรูทั้งหมด ตามจำนวน 'ไก่ดิบ' ที่ยังอยู่บนการต่อสู้"
    },
    {
      "id": 139403,
      "name": "เนื้อไก่เปราะบาง",
      "desc": "เมื่ออวัยวะพังเสียหาย จะได้รับ [Vulnerable] 1 หน่วยทุกเทิร์น ตามจำนวน 'ไก่ดิบ' ที่ตายไปก่อนที่อวัยวะดังกล่าวจะถูกทำลาย"
    },
    {
      "id": 139404,
      "name": "ลูกไก่ทรงพลัง",
      "desc": "หากอวัยวะยังไม่ถูกทำลาย จะได้รับ [AttackDmgUp] 1 หน่วย ตามจำนวน 'ไก่ดิบ' ที่ยังมีชีวิตอยู่"
    },
    {
      "id": 139501,
      "name": "ไก่บองกี้กร่างไปทั่ว",
      "desc": "จบเทิร์น: สร้างความเสียหาย SP 3 หน่วยแก่ศัตรูหนึ่งตัวแบบสุ่ม"
    },
    {
      "id": 139701,
      "name": "ไก่บองกี้กล้ามล่ำ",
      "desc": "จบเทิร์น: มอบ [AttackDmgUp] 2 หน่วย และ [Protection] 2 หน่วยให้กับพันธมิตรทั้งหมดในเทิร์นถัดไป (รวมถึงตัวละครนี้)"
    },
    {
      "id": 141001,
      "name": "กระสอบโลหิต",
      "desc": "หากตัวละครนี้มี [BloodPocket]:\n- ตัวคูณความต้านทานธาตุโทสะของ 'ลำตัว' ลดลง -50%\n- ตัวคูณความต้านทานธาตุโศกาของ 'ลำตัว' เพิ่มขึ้น +50%"
    },
    {
      "id": 141002,
      "name": "กระสอบของไหล",
      "desc": "หากตัวละครนี้มี [WaterPocket] แกนหลักของมันจะฟื้นฟู HP (ปริมาณทับซ้อน x 20) หน่วย"
    },
    {
      "id": 141003,
      "name": "ถุงเลือดฉีกกระชาก",
      "desc": "เมื่ออวัยวะ 'ลำตัว' ถูกทำลาย เมื่อแคลชชนะจะทำให้ [Laceration] บนตัวเป้าหมายทำงานหนึ่งครั้ง และลดจำนวนครั้ง [Laceration] บนตัวเป้าหมายลง 1 หน่วย"
    },
    {
      "id": 141004,
      "name": "สาดกระเซ็นทั่ว",
      "desc": "มอบ [PlayingWithWaterTogetherMirror] 1 หน่วยให้กับเป้าหมายที่แคลชกับสกิลของตัวละครนี้ ด้วยสกิลที่มีประเภทการโจมตีเดียวกัน (มีผลสกิลละครั้ง; มีผล 3 ครั้ง/เทิร์น)\n- หากเป็นสกิลประเภททุบ จะมอบ [PlayingWithWaterTogetherMirror] 2 หน่วยแทน"
    },
    {
      "id": 141101,
      "name": "กระสอบของไหล",
      "desc": "หากตัวละครนี้มี [WaterPocket] แกนหลักของมันจะฟื้นฟู HP (ปริมาณทับซ้อน x 30) หน่วย"
    },
    {
      "id": 141102,
      "name": "ถุงเลือดฉีกกระชาก",
      "desc": "เมื่ออวัยวะ 'ลำตัว' ถูกทำลาย เมื่อแคลชชนะจะทำให้ [Laceration] บนตัวเป้าหมายทำงานสองครั้ง และลดจำนวนครั้ง [Laceration] บนตัวเป้าหมายลง 2 หน่วย"
    },
    {
      "id": 141201,
      "name": "กระสอบโลหิต",
      "desc": "หากตัวละครนี้มี [BloodPocket]:\n- ตัวคูณความต้านทานธาตุโทสะของ 'ลำตัว' ลดลง -35%\n- ตัวคูณความต้านทานธาตุโศกาของ 'ลำตัว' เพิ่มขึ้น +35%"
    },
    {
      "id": 141202,
      "name": "กระสอบของไหล",
      "desc": "หากตัวละครนี้มี [WaterPocket] แกนหลักของมันจะฟื้นฟู HP (ปริมาณทับซ้อน x 35) หน่วย"
    },
    {
      "id": 141203,
      "name": "ถุงเลือดฉีกกระชาก",
      "desc": "เมื่ออวัยวะ 'ลำตัว' ถูกทำลาย เมื่อแคลชชนะจะทำให้ [Laceration] บนตัวเป้าหมายทำงานสามครั้ง และลดจำนวนครั้ง [Laceration] บนตัวเป้าหมายลง 3 หน่วย"
    },
    {
      "id": 141204,
      "name": "สาดตู้มสาดต้ามตู้มต้าม",
      "desc": "หากเป้าหมายไม่มี [PlayingWithWaterTogetherMirror] ตนเองจะได้รับเอฟเฟกต์ดังต่อไปนี้:\n- สร้างความเสียหายเพิ่มขึ้น +80%\n- เมื่อเหรียญสุดท้ายของสกิลโจมตีโดน จะทำให้เกิด [VibrationExplosion]; จากนั้นลดจำนวนครั้ง [Vibration] บนตัวเป้าหมายลง 1 หน่วย\n\nหากเป้าหมายมี [PlayingWithWaterTogetherMirror] ตนเองจะได้รับเอฟเฟกต์ดังต่อไปนี้:\n- สร้างความเสียหายลดลง -50%\n- ได้รับความเสียหายเพิ่มขึ้น +10% ตามทุก ๆ ปริมาณ [PlayingWithWaterTogetherMirror] ที่เป้าหมายมี (สูงสุด 100%)\n\nหากไม่มีผู้ใดเลยที่มี [PlayingWithWaterTogetherMirror] ตนเองจะได้รับเอฟเฟกต์ดังต่อไปนี้:\n- เมื่อโจมตีโดนด้วยสกิล จะสร้างค่า [Laceration] 5 หน่วย\n- เมื่อเหรียญสุดท้ายของสกิลโจมตีโดน จะทำให้ [Laceration] ทำงานหนึ่งครั้ง; จากนั้นลดจำนวนครั้ง [Laceration] บนตัวเป้าหมายลง 1 หน่วย"
    }
  ]
}