{
  "dataList": [
    {
      "id": 2010111,
      "name": "เงียบเสียง",
      "desc": "เมื่อถูกโจมตี จะได้รับ [Binding] 3 หน่วยในเทิร์นถัดไป และเมื่อโจมตีเป้าหมายจะสร้างความเสียหายเพิ่มขึ้น +20% หากเป้าหมายมีตัวคูณความต้านทานประเภทการโจมตีกายภาพหรือธาตุ ต่อสกิลดังกล่าวอยู่ที่ 'อ่อนแอ (x1.5)' หรือ 'รุนแรง (x2.0)'\n(มีผลเทิร์นละครั้ง)"
    },
    {
      "id": 2010211,
      "name": "ถ่านคุกรุ่น",
      "desc": "เมื่อแคลชสกิลชนะ: สร้างค่า [Combustion] เท่ากับ (สั่นพ้องสมบูรณ์ธาตุโทสะ / 2) หน่วย\n(มีผลสกิลละครั้ง)"
    },
    {
      "id": 2010311,
      "name": "ท่านปู่ศิลา",
      "desc": "เมื่อเริ่มเทิร์น จะได้รับ [HitTakeDamageDown] และ [AmberTakeDamageDown] \nอย่างละ 3 หน่วย"
    },
    {
      "id": 2020111,
      "name": "เบื่อหน่าย",
      "desc": "หากศัตรูติดชะงักระหว่างการโจมตีของตัวละครนี้:\nพันธมิตร 1 คนที่มี SP ต่ำที่สุดจะได้รับ [MentalSystemResultIncrease_Typo] +2 หน่วย ในเทิร์นถัดไป (มีผลสูงสุด 3 ครั้งต่อเทิร์น)"
    },
    {
      "id": 2020211,
      "name": "ผ้าคลุมเหลว",
      "desc": "เมื่อเริ่มเทิร์น มอบ [Protection] 2 หน่วยให้กับพันธมิตรที่มีเลือดต่ำที่สุด (รวมตนเอง)"
    },
    {
      "id": 2020311,
      "name": "เจ็บนะ!",
      "desc": "สร้างความเสียหายเพิ่มขึ้น +10% ตามทุก ๆ ประเภทสถานะผิดปกติที่ตัวละครนี้มี (สูงสุด 50%)"
    },
    {
      "id": 2030111,
      "name": "ความทะเยอทะยานเลยเถิด",
      "desc": "เมื่อโจมตีโดน หากเป้าหมายมี [Laceration] จะฟื้นฟูเลือด 3 หน่วย"
    },
    {
      "id": 2030211,
      "name": "กระแสคลื่นแห่งความสิ้นหวัง",
      "desc": "เป้าหมายของสกิลขวาสุดของตัวเองบนกระดานสกิล\nจะเสีย SP เท่ากับ (2 x สั่นพ้องสมบูรณ์ธาตุโศกา) หน่วยหลังการโจมตีจบลง\n(เป้าหมายที่ไม่มีค่า SP จะได้รับความเสียหายธาตุโศกาแทน)"
    },
    {
      "id": 2040111,
      "name": "ศิลป์",
      "desc": "สร้างและรับความเสียหายเพิ่มขึ้น +5% ตามจำนวนศัตรูที่ตัวละครนี้กำจัดไปในเทิร์นก่อน"
    },
    {
      "id": 2040211,
      "name": "ไม้ขีดไฟก้านที่ 4",
      "desc": "ทุกครั้งที่ใช้สกิลครั้งที่ 4 จะได้รับแต้มจบสกิล +4 แต้ม และทุกการโจมตีของสกิลดังกล่าวจะสร้างค่า [Combustion] 4 หน่วยควบไปด้วย"
    },
    {
      "id": 2050111,
      "name": "ปฏิเสธการตัดสิน",
      "desc": "เมื่อเริ่มการต่อสู้ หากตัวละครนี้ถูกเล็งโดยสกิล 3 สกิลหรือมากกว่านั้น \nจะได้รับ [Protection] 3 หน่วย"
    },
    {
      "id": 2050211,
      "name": "ปรับแต่งครั้งสุดท้าย",
      "desc": "หากสกิล E.G.O <น็อตหลุดแล้วหวดใหญ่> ถูกใช้ในขณะที่มีเลือดต่ำกว่า 25% จะได้รับ [Enhancement], [Endurance] และ [Agility] \nอย่างละ 3 หน่วยทุกเทิร์น แต่จะตายทันทีหลังผ่านไป 3 เทิร์น"
    },
    {
      "id": 2050311,
      "name": "วิวรณ์จากเบื้องบน",
      "desc": "หลังจากชนะการแคลชด้วยสกิลซ้ายสุดของตัวเองบนกระดานสกิล \nจะมอบ [Enhancement] หรือ [Endurance] 1 หน่วย\nให้กับพันธมิตร 1 คนแบบสุ่มในเทิร์นถัดไป"
    },
    {
      "id": 2060111,
      "name": "ระลอกคลื่น",
      "desc": "เมื่อเริ่มการต่อสู้ จะฟื้นฟู SP พันธมิตรคนที่มี SP ต่ำที่สุด เท่ากับปริมาณสกิลในสั่นพ้องสมบูรณ์สูงสุด (ไม่รวมตัวตนที่กำลังอยู่ในสภาวะแตกตื่น)"
    },
    {
      "id": 2060211,
      "name": "ริบบิ้นรั้งพันธนา",
      "desc": "เป้าหมายของสกิลซ้ายสุดของตนเองบนกระดานสกิล\nจะได้รับ [ScarletTakeDamageUp] จำนวน (สั่นพ้องสมบูรณ์ธาตุราคะ / 4) หน่วย ในเทิร์นถัดไป"
    },
    {
      "id": 2070111,
      "name": "จิตวิญญาณแห่งการประชัน",
      "desc": "เมื่อพันธมิตรคนอื่นกำจัดศัตรูได้\nจะได้รับ [Enhancement] 1 หน่วย และ [Agility] 1 หน่วยเมื่อเริ่มเทิร์นถัดไป (สูงสุด 3 หน่วย)"
    },
    {
      "id": 2070211,
      "name": "คำราม",
      "desc": "หลังจากกำจัดศัตรูได้แล้ว จะได้รับจำนวน [Charge] เท่ากับครึ่งหนึ่งของจำนวนสกิลในสั่นพ้องสมบูรณ์ธาตุริษยาของเทิร์นนั้น\n(สั่นพ้องสมบูรณ์ธาตุริษยา / 2)"
    },
    {
      "id": 2080111,
      "name": "สถานการณ์บีบบังคับ",
      "desc": "แต้มแคลชสกิลเพิ่มขึ้น +2 แต้ม หากตัวละครนี้เป็นฝ่ายได้เปรียบ\nแต้มแคลชสกิลลดลง -2 แต้ม หากตัวละครนี้เป็นฝ่ายเสียเปรียบ"
    },
    {
      "id": 2080211,
      "name": "ริบบิ้นสีชมพู",
      "desc": "เมื่อแคลชชนะ จะสร้าง [PinkRibbon_Ishmael] 1 หน่วย"
    },
    {
      "id": 2080311,
      "name": "อาบไล้เพลิงไฟ",
      "desc": "เมื่อโจมตีโดน \nหากเป้าหมายมี [Combustion] จะสร้างค่า [Combustion] +1 หน่วยแก่ศัตรู 3 คนแบบสุ่ม"
    },
    {
      "id": 2090111,
      "name": "แตกแยก",
      "desc": "[MentalSystemResultIncrease_Typo] +1 หน่วย \nแต่ในขณะเดียวกัน [MentalSystemResultDecrease_Typo] ก็จะลดลงไปอีก -1 หน่วยด้วยเช่นกัน"
    },
    {
      "id": 2090211,
      "name": "ประกายเพลิง",
      "desc": "หลังจากกำจัดศัตรูที่มี [Combustion] \nจะฟื้นฟูเลือดเท่ากับ (สั่นพ้องสมบูรณ์ธาตุโทสะ)% ของเลือดสูงสุด"
    },
    {
      "id": 2090311,
      "name": "เหน็บหนาวจับใจ",
      "desc": "เมื่อโจมตีโดน หากเป้าหมายมีค่า [Sinking] 5+ หน่วย \nจะสร้าง [Binding] และ [Reduction] อย่างละ 1 หน่วย \n(มีผล 3 ครั้งต่อแต่ละตัวละคร)"
    },
    {
      "id": 2100111,
      "name": "จิตใจไม่คงที่",
      "desc": "ภายในสกิลเดียวกัน หากเหรียญของสกิลนี้ทอยได้คนละด้านกับเหรียญก่อนหน้า จะเสีย SP 5 หน่วย และได้รับ [AttackDmgUp] 1 หน่วยในเทิร์นนี้\n(สูงสุด 3 ครั้งต่อเทิร์น)"
    },
    {
      "id": 2100211,
      "name": "เซ่นชีวิต",
      "desc": "หลังจากกำจัดศัตรูด้วยสกิลโจมตีหรือสกิลสวนกลับ\nจะได้รับทรัพยากร E.G.O ของธาตุสกิลนั้น +5 หน่วย"
    },
    {
      "id": 2110111,
      "name": "กลยุทธ์สมบูรณ์แบบ",
      "desc": "หากตัวละครนี้ไม่ถูกโจมตีเลยตลอดทั้งเทิร์น \nจะได้รับ [AttackDmgUp] 1 หน่วยในเทิร์นถัดไป (ทับซ้อนได้สูงสุด 3 หน่วย)"
    },
    {
      "id": 2110211,
      "name": "กิ่งก้านแห่งความเคลือบแคลง",
      "desc": "เมื่อเริ่มเทิร์น จะได้รับ [PenetrateDamageUp] 1 หน่วย\nเมื่อโจมตีโดนด้วยเหรียญทอยหัว จะสร้าง [Binding] 1 หน่วย\nและจำนวนครั้ง [Burst] +1 หน่วยในเทิร์นถัดไป"
    },
    {
      "id": 2110311,
      "name": "ว่างเปล่า",
      "desc": "เมื่อเริ่มเทิร์น จะได้รับ [ScarletDamageUp] 1 หน่วย\nจะได้รับอีก 1 หน่วยหากมี SP ต่ำกว่า 0 หน่วย"
    },
    {
      "id": 2120111,
      "name": "การเปลี่ยนสภาพที่ควบคุมไม่ได้",
      "desc": "เมื่อเริ่มเทิร์น หากมีเลือดต่ำกว่า 25% จะฟื้นฟูเลือด 15 หน่วย\nและได้รับ [Protection] 2 หน่วย\nเมื่อเอฟเฟกต์นี้ทำงาน จะสุ่มทำให้พันธมิตรคนอื่น 1 คน และศัตรู 1 คนได้รับ [MentalSystemResultDecrease_Typo] -2 แต้ม"
    },
    {
      "id": 2120211,
      "name": "เหล่าตัวหนอนแมลง",
      "desc": "เมื่อโจมตีโดน มีโอกาส (สั่นพ้องสมบูรณ์ธาตุตะกละ x 8)% \nที่จะสร้าง [Muckworm] 5 หน่วย"
    },
    {
      "id": 2120311,
      "name": "ดูดซับสารอาหาร",
      "desc": "หลังจากกำจัดเป้าหมายที่มี [Burst]\nจะฟื้นฟูเลือดเท่ากับ (สั่นพ้องสมบูรณ์ธาตุตะกละ)% ของเลือดสูงสุด"
    },
    {
      "id": 2030311,
      "name": "ปลดปล่อยส่งเดช",
      "desc": "เมื่อเริ่มการต่อสู้ พันธมิตร 1 คนแบบสุ่มที่มี [Charge] \nจะได้รับจำนวน [Charge] +(สั่นพ้องสมบูรณ์ธาตุริษยา / 2) หน่วย"
    },
    {
      "id": 2020411,
      "name": "ปรับตัวเพื่อปลดปล่อย",
      "desc": "ขณะที่ตัวละครนี้มี [Charge] อยู่\nจะสร้างความเสียหายเพิ่มขึ้น +2% ตามทุก ๆ จำนวน [Charge] ที่มี\n\nสกิลต่าง ๆ จะผลาญจำนวน [Charge] ลดลง -2 หน่วย"
    },
    {
      "id": 2030411,
      "name": "กาน้ำอัดอาหารเต็มใบ",
      "desc": "เมื่อเริ่มเทิร์น จะแปลงทรัพยากร E.G.O ที่ไม่ใช่ธาตุราคะแบบสุ่ม 2 หน่วย ให้กลายเป็นทรัพยากร E.G.O ธาตุราคะ +1 หน่วย"
    },
    {
      "id": 2100311,
      "name": "สตูว์หกเรี่ยราด",
      "desc": "เหรียญทอยก้อยจะสร้างค่า [Combustion] 1 หน่วยเมื่อโจมตีโดนศัตรู"
    },
    {
      "id": 2010411,
      "name": "มนุษย์ผู้เดินเตร่",
      "desc": "เมื่อเริ่มเทิร์น หากตัวละครนี้ไม่ได้รับความเสียหายใดเทิร์นก่อนหน้า\nจะได้รับจำนวน [Charge] +4 หน่วย\n\nหลังจากโจมตีโดนศัตรูที่มีค่าความเร็วต่ำกว่าตนเอง\nจะสร้างจำนวนครั้ง [Burst] +1 หน่วย (มีผล 3 ครั้งต่อเทิร์น)"
    },
    {
      "id": 2060311,
      "name": "ปรากฏการณ์ฟื้นฟูพัวพัน",
      "desc": "เมื่อโจมตีโดนศัตรูที่มีสถานะผิดปกติ ตัวละครนี้จะได้รับจำนวน [Charge] +1 หน่วย (สูงสุด +4 หน่วยต่อเทิร์น)\n\nเมื่อเลือดต่ำกว่า 0 เป็นครั้งแรกในการเผชิญหน้า จะผลาญจำนวน [Charge] ทั้งหมด และฟื้นฟูเลือดตามอัตราส่วนปริมาณที่ผลาญไป (ไม่สามารถฟื้นฟูเกิน 25% ของเลือดสูงสุดได้)"
    },
    {
      "id": 2050411,
      "name": "หงุดหงิดไร้สิ่งใดดับได้",
      "desc": "เมื่อเริ่มการต่อสู้ หากถูกเล็งโดยสกิล 2 สกิลหรือมากกว่านั้น \nตัวละครนี้จะได้แต้มเริ่มต้นสกิลเพิ่มขึ้น +1 แต้ม\nและเมื่อถูกโจมตีจะสร้างค่า [Combustion] 1 หน่วยแก่ผู้โจมตี (สูงสุด 5 ครั้งต่อเทิร์น)"
    },
    {
      "id": 2080411,
      "name": "ปราบปรามกลางเสียงเชียร์",
      "desc": "เมื่อโจมตีเป้าหมายที่มีเลือดต่ำกว่า 30%\nสกิลธาตุโทสะจะสร้างความเสียหายเพิ่มขึ้น +20%"
    },
    {
      "id": 2110411,
      "name": "ลมหายใจแห่งการออกล่า",
      "desc": "หลังจากการแคลช จะได้รับค่า [Breath] 2 หน่วย\n\nหากติดชะงักจะได้รับ [Protection] 2 หน่วย\nและเมื่อฟื้นตัวจากการชะงักจะได้รับค่า [Breath] 5 หน่วย"
    },
    {
      "id": 2070311,
      "name": "คายประจุไม่แน่นอน",
      "desc": "เมื่อถูกโจมตี จะผลาญจำนวน [Charge] 1 หน่วยเพื่อฟื้นเลือด 2.5% ของเลือดสูงสุด\n- ขณะที่มีเลือดต่ำกว่า 40% จะได้รับจำนวน [Charge] 1 หน่วย ก่อนที่จะใช้งานเอฟเฟกต์ฟื้นฟูเลือด \n(สามารถรับจำนวน [Charge] ได้สูงสุด 10 หน่วยต่อเทิร์น)"
    },
    {
      "id": 2120411,
      "name": "เปลี่ยนรูปแบบคายประจุ",
      "desc": "เมื่อโจมตีโดนด้วยเหรียญทอยหัว จะผลาญจำนวน [Charge] 2 หน่วย เพื่อมอบจำนวน [Charge] +1 หน่วยให้กับพันธมิตรที่กำลังถือครอง [Charge] จำนวนต่ำที่สุดอยู่"
    },
    {
      "id": 2010511,
      "name": "แสงตะวันหลังฝน",
      "desc": "เมื่อเริ่มเทิร์น พันธมิตรทั้งหมดฟื้นฟูจะ SP จำนวน 3 หน่วย"
    },
    {
      "id": 2040311,
      "name": "ใยแมงมุม",
      "desc": "เมื่อแคลชสกิลชนะ จะสร้าง [Binding] 1 หน่วยในเทิร์นถัดไป (มีผล 3 ครั้งต่อเทิร์น)"
    },
    {
      "id": 2040411,
      "name": "ผู้ล่า",
      "desc": "หากตัวละครนี้ฟื้นฟูเลือดมากกว่า 10% ของเลือดสูงสุดตนเองในเทิร์นนี้\nจะได้รับ [Enhancement] 1 หน่วยในเทิร์นถัดไป"
    },
    {
      "id": 2040511,
      "name": "กระป๋องที่ถูกเปิดออก",
      "desc": "เมื่อโจมตีโดน หากเป้าหมายมีค่า [Sinking] 5+ หน่วย\nจะสร้าง [Disarming] 1 หน่วย (5 ครั้งต่อเทิร์น)"
    },
    {
      "id": 2060411,
      "name": "นกนางนวลร้องระงมให้กับผืนทะเลแสนไกล",
      "desc": "เมื่อศัตรูถูกกำจัด พันธมิตรที่มี SP ต่ำที่สุดจะฟื้นฟู SP 1 หน่วย\nเมื่อใดก็ตามที่ศัตรูถูกกำจัด ปริมาณ SP ที่ฟื้นฟูจะเพิ่มขึ้น 2 หน่วย (สูงสุด 9 หน่วย)\n(ปริมาณดังกล่าวจะรีเซ็ตเมื่อเริ่มการต่อสู้เวฟใหม่)"
    },
    {
      "id": 2100411,
      "name": "การล่อลวงของนางฟ้า",
      "desc": "หลังจากกำจัดศัตรูที่เล็งตัวละครนี้เป็นเป้าหมายหลักในตอนเริ่มการต่อสู้แล้ว\nจะฟื้นฟูเลือด (3 + (สั่นพ้องสมบูรณ์ธาตุตะกละ))%"
    },
    {
      "id": 2070411,
      "name": "ฌาน",
      "desc": "เมื่อฟื้นตัวจากสภาวะชะงัก จะเพิ่มเลือดสูงสุดขึ้น 15% ของเลือดสูงสุดเริ่มต้นของตัวตนนี้\nจากนั้นจะฟื้นฟูเลือด 15% ของเลือดสูงสุดปัจจุบัน\n- หากมีเลือดต่ำกว่า 30% ของเลือดสูงสุดปัจจุบัน จะฟื้นฟูเลือด 25% แทน\n(มีผล 3 ครั้งต่อการเผชิญหน้า; เมื่อจบการเผชิญหน้าจะแปลงเลือดกลับสู่เลือดสูงสุดเริ่มต้น ปริมาณเลือดจะถูกปรับเพื่อสะท้อนเปอร์เซ็นต์เลือดในตอนที่การเผชิญหน้าจบลง)"
    },
    {
      "id": 2050511,
      "name": "โกรธาที่ถูกผูกมัด",
      "desc": "สกิลซ้ายสุดของตัวละครนี้บนกระดานสกิลจะเสียแต้มเริ่มต้นสกิล -1 แต้ม และแต้มเหรียญจะเพิ่มขึ้น +2 แต้ม\n\nเมื่อเริ่มเทิร์น หากมีค่าความเร็วต่ำกว่า 4- หน่วย จะได้รับ [HitResultUp] 1 หน่วย"
    },
    {
      "id": 2020511,
      "name": "ตีตราเพลิง",
      "desc": "เมื่อโจมตีทอยหัวด้วยสกิลธาตุราคะ จะสร้างค่า [Combustion] 1 หน่วยแก่เป้าหมาย \n(มีผล 6 ครั้งต่อเทิร์น)"
    },
    {
      "id": 2060511,
      "name": "เมือกเขียว",
      "desc": "เมื่อถูกโจมตีในขณะที่มีเลือดต่ำกว่า 50% จะสร้างค่า [Burst] 1 หน่วย แก่ผู้โจมตี \n(ทำงาน (สั่นพ้องสมบูรณ์สูงสุดธาตุตะกละ) ครั้งต่อเทิร์น)"
    },
    {
      "id": 2040611,
      "name": "กลืนกินความฝัน",
      "desc": "เมื่อโจมตีคริติคอลด้วยสกิลธาตุอัตตา จะได้รับจำนวนครั้ง [Breath] 1 หน่วย \n(มีผล 3 ครั้งต่อเทิร์น)"
    },
    {
      "id": 2080511,
      "name": "การเดินเรืออันแสนบ้าบิ่น",
      "desc": "เมื่อจบเทิร์น จะสร้างค่า [Sinking] 5 หน่วยแก่พันธมิตรคนอื่น 1 คนที่มีเลือดต่ำที่สุด และมอบ [Agility] 1 หน่วย กับ [AttackUp] 3 หน่วยให้ในเทิร์นถัดไป"
    },
    {
      "id": 2090411,
      "name": "โสโครกหนึบหนับ",
      "desc": "เมื่อโจมตีทอยหัวด้วยสกิลประเภทแทง จะสร้าง [Binding] 1 หน่วย (2 ครั้งต่อเทิร์น)"
    },
    {
      "id": 2100511,
      "name": "คำทำนายแห่งความบรรลัย",
      "desc": "เมื่อโจมตีทอยหัวด้วยสกิลธาตุราคะ\nจะลด SP ของตัวละครนี้และเป้าหมายลง 4 หน่วย (ไม่มีผลกับเป้าหมายที่ไม่มีค่าสติ)\n\nเมื่อกำจัดศัตรูได้ด้วยสกิลธาตุราคะ\nจะได้รับทรัพยากร E.G.O ธาตุราคะเพิ่มขึ้น +5 หน่วย"
    },
    {
      "id": 2090511,
      "name": "คำพิพากษาจากเบื้องบน",
      "desc": "เมื่อใดก็ตามที่ศัตรูติดชะงัก\nพันธมิตรที่มีเปอร์เซ็นต์เลือดต่ำที่สุดจะฟื้นฟูเลือดเท่ากับ 4% ของเลือดสูงสุดพันธมิตรคนนั้น (มีผลเทิร์นละครั้ง)"
    },
    {
      "id": 2070511,
      "name": "ความเกลียดชังไร้สิ้นสุด",
      "desc": "เมื่อตัวละครนี้มีเอฟเฟกต์สถานะหรือสถานะผิดปกติ และหากเป้าหมายหลักหรือผู้โจมตีมีเอฟเฟกต์ด้านบวก:\n- เอฟเฟกต์สกิลหรือเอฟเฟกต์เหรียญจะสร้างค่า [Combustion], [Laceration], [Vibration], [Burst] และ [Sinking] มากขึ้น +1 หน่วย\n- เอฟเฟกต์สกิลหรือเอฟเฟกต์เหรียญจะทำให้ได้รับค่า [Breath] และจำนวน [Charge] มากขึ้น +1 หน่วย"
    },
    {
      "id": 2110511,
      "name": "ของขวัญแสนสวย",
      "desc": "เมื่อมอบเอฟเฟกต์บัพให้กับพันธมิตรคนอื่นผ่านเอฟเฟกต์สกิลหรือเอฟเฟกต์เหรียญ จะสุ่มเลือกหนึ่งในสถานะต่อไปนี้: \n[Combustion], [Laceration], [Vibration], [Burst] หรือ [Sinking]\n\nจากนั้น สร้างค่าสถานะดังกล่าว 1 หน่วยแก่ศัตรู 1 คนแบบสุ่ม\n(ทำงาน 5 ครั้งต่อเทิร์น และสามารถสร้างได้สูงสุด 5 ครั้งต่อศัตรูหนึ่งตัว;\nสำหรับสิ่งผิดปกติ จะมีผลกับชิ้นส่วนอวัยวะแบบสุ่ม)"
    },
    {
      "id": 2030511,
      "name": "เจดีย์หินร่วงหล่น",
      "desc": "ได้รับค่า [Breath] 2 หน่วย และจำนวนครั้ง [Breath] +2 หน่วย\nเมื่อกำจัดศัตรูที่มี [Laceration] (มีผล 3 ครั้งต่อเทิร์น)"
    },
    {
      "id": 2120511,
      "name": "มงกุฎกุหลาบ",
      "desc": "เริ่มเทิร์น: สร้างค่า [Burst] 2 หน่วยแก่ศัตรู 1 ตัวแบบสุ่ม (ในการเผชิญหน้าเพ่งเล็ง จะมีผลกับชิ้นส่วนอวัยวะทั้งหมด)\n\nเมื่อทำให้เกิดสั่นพ้องสมบูรณ์ จะสร้างค่า [Burst] 2 หน่วยแก่ศัตรูทั้งหมดเมื่อเริ่มการต่อสู้"
    },
    {
      "id": 2120611,
      "name": "หากฉันกลับไปได้ล่ะก็...",
      "desc": "หลังโจมตี: หากเป้าหมายถูกกำจัดหลังจากการโจมตีของตัวละครนี้ \nทรัพยากร E.G.O ที่มีอยู่น้อยที่สุดจะได้รับทรัพยากร E.G.O +1 หน่วย\n- ได้รับทรัพยากร E.G.O เพิ่มเติมอีก +1 หน่วย\nตามทุก ๆ (ค่า + จำนวนครั้ง [Sinking]) 5 หน่วย (สูงสุด 3 หน่วย)\n(หากมี 'ทรัพยากร E.G.O ที่มีอยู่น้อยที่สุด' อยู่ 2 ธาตุหรือมากกว่านั้น จะสุ่มให้ 1 ในธาตุเหล่านั้นได้รับทรัพยากร E.G.O)"
    },
    {
      "id": 2010611,
      "name": "วันวานที่แตกหัก",
      "desc": "หากเป้าหมายมีค่า [Sinking] 6+ หน่วย แต้มแคลชสกิลจะเพิ่มขึ้น +1 แต้ม\nหากเป้าหมายมีจำนวนครั้ง [Sinking] 4+ หน่วย แต้มแคลชสกิลจะเพิ่มขึ้น +1 แต้ม"
    },
    {
      "id": 2030611,
      "name": "เสียงกรีดร้องอันปั่นป่วน",
      "desc": "หากเป้าหมายถูกกำจัดด้วยสกิลประเภทฟันหรือสกิลธาตุริษยาของตัวละครนี้ จะได้รับ [Enhancement] 1 หน่วยในเทิร์นถัดไป (มีผลเทิร์นละครั้ง)"
    },
    {
      "id": 2050611,
      "name": "สายเคเบิลเกินพิกัด",
      "desc": "เริ่มการต่อสู้: ขณะที่มีสั่นพ้อง 4+ สกิล จะได้รับ [AttackUp] 2 หน่วย และ [DefenseUp] 2 หน่วย\n- หากการสั่นพ้องสกิลดังกล่าวเป็นการสั่นพ้องธาตุริษยา จะมอบเอฟเฟกต์ข้างต้นให้กับพันธมิตร 2 คน ที่อยู่ติดกับตัวละครนี้บนกระดานสกิลด้วยเช่นกัน"
    },
    {
      "id": 2070611,
      "name": "โซ่ตรวนแห่งการผูกรั้ง",
      "desc": "เริ่มการต่อสู้: ขณะที่มีสั่นพ้องสูงสุด 4+ สกิล (รวมสกิลของตัวละครนี้อยู่ในนั้นด้วย) จะมอบ [AttackUp] 3 หน่วย และ [DefenseUp] 3 หน่วย ให้กับตนเองและพันธมิตรทั้งหมดที่เป็นส่วนหนึ่งของการสั่งพ้องดังกล่าว\n- หากการสั่นพ้องดังกล่าวเป็นการสั่นพ้องสมบูรณ์\nจะมอบ [AttackUp] และ [DefenseUp] เพิ่มเติมอีกอย่างละ 2 หน่วย"
    },
    {
      "id": 2110611,
      "name": "เปิดโถงต้อนรับอย่างยิ่งใหญ่",
      "desc": "หลังจากตัวละครนี้โจมตี:\nหากเป้าหมายติดชะงักหรือถูกกำจัด จะได้รับทรัพยากร E.G.O ธาตุอัตตา +1 หน่วย\nและทรัพยากรธาตุอื่น 1 ธาตุแบบสุ่ม +1 หน่วย (3 ครั้งต่อเทิร์น)"
    },
    {
      "id": 2080611,
      "name": "ตะกละตะกลาม",
      "desc": "หากเป้าหมายหลักได้รับความเสียหายเลือดในเทิร์นนี้ และไม่ได้มีเลือดเต็มจำนวนในตอนที่ใช้สกิล:\nเมื่อโจมตีโดน\n- หากตัวละครนี้มีเลือดเต็มจำนวน จะสร้างความเสียหายเพิ่มขึ้น +5~10%\n- หากตัวละครนี้ไม่ได้มีเลือดเต็มจำนวน จะฟื้นฟูเลือด 2~5 หน่วย\n(มีผล 7 ครั้งต่อเทิร์น)",
      "summary": "หากเป้าหมายไม่ได้มีเลือดเต็มจำนวน การโจมตีโดนจะสร้างความเสียหายมากขึ้นหรือไม่ก็ฟื้นฟูเลือด"
    },
    {
      "id": 2090611,
      "name": "หลงใหลครอบงำ",
      "desc": "สกิลซ้ายสุดของตัวละครนี้บนกระดานสกิลจะสร้างค่า [Laceration] เพิ่มขึ้น เป็นสองเท่า (เทิร์นละครั้ง)",
      "summary": "สกิลนี้สร้างค่า [Laceration] เพิ่มขึ้น x2"
    },
    {
      "id": 2060611,
      "name": "โศกเศร้าโศกา",
      "desc": "หากตัวละครนี้ใช้สกิลที่ทำให้เกิด [VibrationExplosion] บนตัวศัตรู\nจะสร้าง [AttackDown] 1 หน่วย และ [DefenseDown] 2 หน่วยแก่ศัตรู ในเทิร์นถัดไป (มีผล 3 ครั้งต่อเทิร์น; รวมถึงสกิล E.G.O)",
      "summary": "เมื่อทำให้เกิด [VibrationExplosion] บนตัวศัตรู\nจะสร้าง [AttackDown] 1 หน่วย และ [DefenseDown] 2 หน่วยในเทิร์นถัดไป"
    },
    {
      "id": 2100611,
      "name": "เยื่อหุ้มน้ำตา",
      "desc": "เริ่มเทิร์น: หากตัวละครนี้มีโล่อยู่ จะได้รับ [Protection] 1 หน่วย\n- หากตัวละครนี้อยู่ใต้เอฟเฟกต์ [ShieldManagerCryingToad] อยู่\nจะได้รับ [Protection] เพิ่มเติมอีก 1 หน่วย",
      "summary": "มีโล่: ได้ [Protection] 1 หน่วย\nมี [ShieldManagerCryingToad]: ได้ [Protection] อีก 1 หน่วย"
    },
    {
      "id": 2020611,
      "name": "เวลายังคงดำเนินต่อ",
      "desc": "หากตัวละครนี้ใช้สกิลที่ทำให้เกิด [VibrationExplosion] บนตัวเป้าหมาย\nจะได้รับ [Agility] 1 หน่วยในเทิร์นถัดไป \n(มีผล 4 ครั้งต่อเทิร์น; รวมสกิล E.G.O ด้วย)",
      "summary": "หากตัวละครนี้ใช้สกิลที่ทำให้เกิด [VibrationExplosion] บนตัวเป้าหมาย\nจะได้รับ [Agility] 1 หน่วยในเทิร์นถัดไป\n(มีผล 4 ครั้งต่อเทิร์น; รวมสกิล E.G.O ด้วย)"
    },
    {
      "id": 2040711,
      "name": "ร่องรอยแห่งการจับจ้อง",
      "desc": "เมื่อใดก็ตามที่ตัวละครนี้ใช้สกิลโจมตีพื้นฐานโจมตีใส่ศัตรู \nจะได้รับทรัพยากร E.G.O เพิ่มเติม +1 หน่วย ของธาตุที่มีทรัพยากรอยู่น้อยที่สุดแบบสุ่ม โดยธาตุที่ได้รับจะต้องไม่สอดคล้องกับธาตุของสกิลโจมตีที่ใช้ (2 ครั้งต่อเทิร์น)"
    },
    {
      "id": 2070711,
      "name": "จี้ห้อยคอที่ถูกบดขยี้",
      "desc": "เริ่มเทิร์น: ขณะที่มีสั่นพ้องสูงสุด 3+ สกิล จะได้รับค่า [Breath] 3 หน่วย"
    },
    {
      "id": 2110711,
      "name": "มนุษย์ผู้เดินเตร่",
      "desc": "จำนวน [Charge] สูงสุด +5 หน่วย\n\nสกิลที่ผลาญจำนวน [Charge] จะสร้างความเสียหายเพิ่มขึ้น +2%\nตามทุก ๆ (ค่า [Charge] - 1) (สูงสุด 10%)",
      "summary": "สกิลที่ผลาญจำนวน [Charge] จะสร้างความเสียหายเพิ่มขึ้น"
    },
    {
      "id": 2120711,
      "name": "อาลัย",
      "desc": "จบเทิร์น:\nหากตัวละครนี้มีสถานะผิดปกติ จะได้รับ [Enhancement] 1 หน่วยในเทิร์นถัดไป\n\nเมื่อโจมตีเป้าหมายที่อยู่ในสภาวะแตกตื่นหรือถูก E.G.O กัดกร่อน: สร้างความเสียหายเพิ่มขึ้น +15%",
      "summary": ""
    },
    {
      "id": 2080711,
      "name": "รับรองแขกไร้บัตรเชิญ",
      "desc": "หากเป้าหมายมีเอฟเฟกต์ [UninvitedGuestPersonality] \nหรือเอฟเฟกต์เปลี่ยนประเภทแตกตื่นใด ๆ ก็ตาม แต้มแคลชสกิลจะเพิ่มขึ้น +1 แต้ม\n\nเมื่อโจมตีโดนเป้าหมายดังกล่าว จะฟื้นฟู SP พันธมิตร 1 คนที่มี SP ต่ำที่สุดเป็นจำนวน 5 หน่วย (มีผลเทิร์นละครั้ง)"
    },
    {
      "id": 2020711,
      "name": "บ่วงบาศแผ่ขยาย",
      "desc": "หลังจากโจมตี หากเป้าหมายติดชะงักหรือถูกกำจัด\nจะสร้างจำนวนครั้ง [Burst] +1 หน่วยแก่ศัตรูแบบสุ่ม 2 คน \n(มีผลเทิร์นละครั้ง; ไม่สามารถทับซ้อนได้; \nและในการเผชิญหน้าเพ่งเล็ง จะมีผลกับชิ้นส่วนอวัยวะ 2 ส่วน)",
      "summary": "หลังจากโจมตี หากเป้าหมายติดชะงักหรือถูกกำจัด จะสร้างจำนวนครั้ง [Burst] +1 หน่วยแก่ศัตรูแบบสุ่ม 2 คน "
    },
    {
      "id": 2060711,
      "name": "ถึงเวลาออกล่า",
      "desc": "หากศัตรูหรือพันธมิตรถูกฆ่าจากความเสียหาย [Burst] หรือ [Laceration] จะสร้าง [Snare] 2 หน่วยแก่ศัตรู 1 คนแบบสุ่ม\nและได้รับ [Agility] 1 หน่วยในเทิร์นถัดไป (มีผลเทิร์นละครั้ง)"
    },
    {
      "id": 2030711,
      "name": "บุปผาแดงชาดแพร่บานทั่วสารทิศ",
      "desc": "ทุกครั้งที่เกิดความเสียหาย [Laceration] 10+ หน่วย\nตนเองจะฟื้นฟู SP 1 หน่วย (10 หน่วยต่อเทิร์น)"
    },
    {
      "id": 2090711,
      "name": "ลิ่มเหล็กตอกหัวใจ",
      "desc": "เมื่อสร้าง [Laceration] หรือ 'เลือดไหลแบบพิเศษ' แก่ศัตรูด้วยสกิลโจมตีพื้นฐาน จะสร้าง [DefenseDown] 1 หน่วย (มีผลเทิร์นละครั้ง)\n- หากเป้าหมายมี [Laceration] หรือ 'เลือดไหลแบบพิเศษ'\nจะสร้างค่า [Laceration] เพิ่มเติมอีก 2 หน่วย (มีผลเทิร์นละครั้ง)\n\nหากพันธมิตร (รวมตัวละครนี้) ได้รับความเสียหายเลือดโดยตรงจากศัตรู\nจะสร้าง [Curse] 1 หน่วยแก่ศัตรูเป้าหมาย (2 ครั้งต่อเทิร์น)",
      "summary": ""
    },
    {
      "id": 2100711,
      "name": "ซ่อนสิ่งเปรอะเปรื้อน",
      "desc": "เริ่มการต่อสู้: หากตัวละครนี้มีสถานะผิดปกติ จะได้รับ [ParryingResultUp] 1 หน่วย และ [Endurance] 1 หน่วย\n- ได้รับ [Protection] 1 หน่วย ตามทุก ๆ สถานะผิดปกติ 3 ประเภทที่ตนเองมี\n(สูงสุด 2 หน่วย)"
    },
    {
      "id": 2050711,
      "name": "งานเลี้ยงกระหายโลหิต",
      "desc": "เมื่อตัวละครนี้สร้างหรือรับความเสียหาย [Laceration] จะฟื้นฟูเลือดเท่ากับความเสียหาย [Laceration] (สูงสุด 10 หน่วยต่อเทิร์น)\n- เมื่อใช้งานเอฟเฟกต์สกิล/เหรียญที่สร้าง [Laceration] ได้\nหากเป้าหมายมี [RoseWedge] อยู่ จะสร้างค่า [Laceration] 1 หน่วยแก่เป้าหมาย\n(2 ครั้งต่อเทิร์น)",
      "summary": "ฟื้นฟูเลือดตามความเสียหาย [Laceration] ที่สร้างหรือได้รับ"
    },
    {
      "id": 2010711,
      "name": "คนต่อไป",
      "desc": "หลังโจมตี: หากเป้าหมายถูกกำจัด จะได้รับจำนวนครั้ง [Breath] +2 หน่วย\n(มีผล 2 ครั้งต่อเทิร์น)",
      "summary": "กำจัดเป้าหมายเพื่อรับจำนวนครั้ง [Breath]"
    },
    {
      "id": 2070811,
      "name": "ระฆังที่พังทลาย",
      "desc": "สร้าง [Vulnerable] ที่มีผลทันทีในเทิร์นนี้แก่ศัตรูที่ได้รับผลของ [VibrationExplosion] จากเอฟเฟกต์สกิล, เหรียญ, หรือพาสซีพ\n- จะไม่ทับซ้อนกับของขวัญ E.G.O ที่จะสร้าง [Vulnerable] เมื่อทำให้เกิด [VibrationExplosion] \n(หากของขวัญ E.G.O ดังกล่าวถูกเสริมขั้นแล้ว จะลบปริมาณของเอฟเฟกต์นี้ออกไปจากปริมาณสุดท้าย ก่อนจะทำการสร้างแก่เป้าหมาย)",
      "summary": "สร้าง [Vulnerable] 1 หน่วยเมื่อทำให้เกิด [VibrationExplosion]"
    },
    {
      "id": 2080811,
      "name": "เงาจับจ้องจากมุมมืด",
      "desc": "พันธมิตรจะได้รับจำนวนครั้ง [Vibration] จากเอฟเฟกต์สกิลหรือเอฟเฟกต์เหรียญเพิ่มขึ้น +1 หน่วย (2 ครั้งต่อเทิร์น)\n- หากเป้าหมายของพันธมิตรคนนั้นติดชะงัก อยู่ในอาการขวัญอ่อน หรือกำลังแตกตื่น จะได้รับจำนวนครั้งเพิ่ม +2 หน่วยแทน\n- เอฟเฟกต์นี้จะไม่ทับซ้อนกับของขวัญ E.G.O ที่มีเอฟเฟกต์แบบเดียวกัน",
      "summary": "พันธมิตรได้รับจำนวนครั้ง [Vibration] เพิ่มขึ้น"
    },
    {
      "id": 2120811,
      "name": "คืนผวาข่มตานอนไม่หลับ",
      "desc": "เริ่มการต่อสู้: สร้าง [AttackDown] 1 หน่วย หรือ [DefenseDown] 1 หน่วย แก่ศัตรูทั้งหมด เป็นจำนวน (จำนวนศัตรูที่ติดชะงัก, ขวัญอ่อน, หรือแตกตื่น) ครั้ง\n(มีผล 2 ครั้งต่อเทิร์น)\n- เอฟเฟกต์นี้จะไม่ทับซ้อนกับของขวัญ E.G.O ที่มีเอฟเฟกต์แบบเดียวกัน",
      "summary": "สุ่มสร้าง [AttackDown] หรือ [DefenseDown]"
    },
    {
      "id": 2110811,
      "name": "กระสุนทั้งเจ็ดนัด",
      "desc": "เมื่อโจมตีโดนด้วยสกิลโจมตีพื้นฐาน:\nสร้างค่า [Combustion] เท่ากับ ([FreischutzShotCount] / 3) หน่วย (3 ครั้งต่อเทิร์น)\n- <สำหรับตัวตน 'E.G.O บริษัทโลโบโตมี:: กระสุนอาคม - อูทิส'>\nสร้างค่า [Combustion] เท่ากับ ([FreischutzShotCount]) หน่วยแทน (3 ครั้งต่อเทิร์น)\n\nหากเป้าหมายมีค่า [Combustion] 30+ หน่วย จะสร้าง [DarkFlame] 1 หน่วย แทนเอฟเฟกต์ข้างต้น (2 ครั้งต่อเทิร์น)",
      "summary": "ช่วยสร้างค่า [Combustion] แต่หากมีมากพอจะสร้าง [DarkFlame] แทน"
    },
    {
      "id": 2040811,
      "name": "ลมหายใจ",
      "desc": "เมื่อเริ่มเทิร์นถัดไปหลังจากใช้สกิล E.G.O นี้: ได้รับ [NebulizerInhale] 1 หน่วย (มีผลเทิร์นละครั้ง)\n- หากสกิลนี้กำจัดศัตรู จะได้รับ [NebulizerInhale] เพิ่มเติม เท่ากับจำนวนเป้าหมายที่ถูกกำจัด\n- หากสกิลนี้กำจัดพันธมิตร จะได้รับ [NebulizerInhale] เพิ่มเติม (เป้าหมายที่ถูกกำจัด x 2) หน่วย\n- ปริมาณของเอฟเฟกต์นี้จะซ้อนทับกันตลอดการเผชิญหน้านี้",
      "summary": "ได้รับ [NebulizerInhale] ผ่านวิธีต่าง ๆ"
    },
    {
      "id": 2020811,
      "name": "ลมหายใจ",
      "desc": "เมื่อเริ่มเทิร์นถัดไปหลังจากใช้สกิล E.G.O นี้: ได้รับ [NebulizerExhale] 1 หน่วย (มีผลเทิร์นละครั้ง)\n- ปริมาณของเอฟเฟกต์นี้จะซ้อนทับกันตลอดการเผชิญหน้านี้\n\nเริ่มการต่อสู้: ได้รับ [NebulizerExhale] 1 หน่วย ทุกครั้งที่ตัวละครนี้มอบจำนวนครั้ง [Breath] รวม 10 หน่วยให้กับพันธมิตร ผ่านเอฟเฟกต์ [NebulizerExhale]\n\nจบเทิร์น: เอฟเฟกต์นี้จะเริ่มจากพันธมิตรที่มีเปอร์เซ็นต์เลือดต่ำที่สุดก่อน โดยจะฟื้นฟูเลือด (ปริมาณทับซ้อนของ [NebulizerExhale])% ให้กับพันธมิตรจำนวน (สั่นพ้องสูงสุด) คน (สูงสุด 6 คน)\n- หากตัวละครที่ได้รับการฟื้นฟูเลือดมีค่า [Breath] 20+ หน่วย จะทำให้ผลฟื้นฟูเลือดทำงานอีก 1 ครั้ง",
      "summary": "มอบจำนวนครั้ง [Breath] ให้พันธมิตรทั้งหมด และฟื้นฟูเลือด"
    },
    {
      "id": 2090811,
      "name": "สุขีโหมเพลิง",
      "desc": "เมื่อเป้าหมายที่มีจำนวนครั้ง [Combustion] 10+ หน่วยถูกกำจัด\nจะสร้างจำนวนครั้ง [Combustion] ของเป้าหมายกระจายแก่ศัตรูทั้งหมด\nและฟื้นฟู SP ตนเอง 8 หน่วย \n(ในการเผชิญหน้าเพ่งเล็ง จะมีผลกระจายกับชิ้นส่วนอวัยวะทั้งหมด; โดยจะเพิ่มจำนวนครั้งได้สูงสุด 3 หน่วยต่อเป้าหมาย และมีผล 2 ครั้งต่อเทิร์น)\n- ขณะที่มี SP สูงสุด จะฟื้นฟู SP พันธมิตร 1 คนที่มี SP ต่ำที่สุดเป็นจำนวน 5 หน่วยแทน",
      "summary": "กระจายจำนวนครั้ง [Combustion] ของเป้าหมายที่ถูกกำจัดแก่ศัตรูทั้งหมด\nและฟื้นฟู SP ตนเอง (กับพันธมิตร)"
    },
    {
      "id": 2030811,
      "name": "ยันต์อ่อนเรี่ยวไร้แรง",
      "desc": "เมื่อสกิลของตัวละครนี้โจมตีโดน: หากเป้าหมายมีค่า [Burst] 15+ หน่วย หรือตัวละครนี้สร้างความเสียหายคริติคอล จะสร้าง [DefenseDown] 1 หน่วย (สูงสุด 6 หน่วย)\n- เมื่อพาสซีพนี้ทำงาน เอฟเฟกต์จะไม่ทับซ้อนกับเอฟเฟกต์ของขวัญ E.G.O ที่ชื่อ \"ตุ๊กตาไม้เก่าแก่\"",
      "summary": "สร้าง [DefenseDown] เมื่อโจมตีศัตรูที่มีค่า [Burst] 15+ หน่วย หรือโจมตีติดคริติคอล"
    },
    {
      "id": 2080911,
      "name": "ย้อนตายด้วยพิษบ่ง",
      "desc": "เมื่อใดก็ตามที่ตัวละครนี้สร้างค่า [Sinking], จำนวนครั้ง [Sinking], หรือ 'จมดิ่งแบบพิเศษ' ผ่านการใช้สกิลโจมตีของตนเอง \nจะได้รับ [AttackUp] 1 หน่วยในเทิร์นถัดไป (สูงสุด 2 หน่วย)\n- ขณะที่มีสั่นพ้องสมบูรณ์ 3+ สกิล หากเกิดเงื่อนไขเดียวกับข้างต้น\nจะได้รับ [AttackUp] 1 หน่วยในเทิร์นถัดไปแทน (สูงสุด 3)",
      "summary": "เมื่อสร้างเอฟเฟกต์ [Sinking] จะได้รับ [AttackUp]"
    },
    {
      "id": 2060811,
      "name": "หยาดน้ำตาไหลริน",
      "desc": "เมื่อเป้าหมายถูกกำจัดหลังจากตัวละครนี้โจมตีหรือใช้สกิลสวนกลับ:\n- ได้รับ [Agility] 2 หน่วยในเทิร์นถัดไป (มีผลเทิร์นละครั้ง)\n- มีผลกับพันธมิตรทั้งหมด (รวมตัวละครนี้): ในเทิร์นถัดไป มอบ 'ความเสียหาย (ประเภทการโจมตีกายภาพ) & (ประเภทธาตุ) เพิ่มขึ้น' อย่างละ 1 หน่วย โดยบัพของเอฟเฟกต์ดังกล่าวจะอิงตามสกิลที่ทำให้เอฟเฟกต์นั้นทำงาน (มีผลเทิร์นละครั้ง)\n- สร้าง [Reduction] 1 หน่วยแก่ศัตรูทั้งหมดในเทิร์นถัดไป (มีผลเทิร์นละครั้ง)\n\nเมื่อตัวละครนี้ตาย:\n- มอบ [ShamrockDamageUp] และ [PenetrateDamageUp] \nอย่างละ 1 หน่วยให้กับพันธมิตรทั้งหมดในเทิร์นถัดไป (มีผลเทิร์นละครั้ง)\n- สร้าง [Reduction] 1 หน่วยแก่ศัตรูทั้งหมดในเทิร์นถัดไป (มีผลเทิร์นละครั้ง)",
      "summary": "มอบบัพให้พันธมิตร และสร้างสถานะผิดปกติแก่ศัตรู\nหากตัวละครนี้กำจัดศัตรู หรือเมื่อตัวละครนี้ตาย"
    },
    {
      "id": 2100811,
      "name": "หยาดน้ำตาไหลริน",
      "desc": "- จบเทิร์น: หากตัวละครนี้มีสถานะผิดปกติ, เสียเลือด, หรือเสีย SP\nจะทำการฟื้นฟู SP ตนเอง 5 หน่วย\n- หากตัวละครนี้หรือพันธมิตรถูกกำจัด:\nสร้าง [Vulnerable] 1 หน่วยแก่ศัตรูทั้งหมดในเทิร์นถัดไป (มีผลเทิร์นละครั้ง)",
      "summary": "เมื่อตนหรือพันธมิตรถูกกำจัด จะสร้าง [Vulnerable] 1 หน่วยแก่ศัตรูทั้งหมด"
    },
    {
      "id": 2030911,
      "name": "วงจรปรับตัวเข้ากับอาร์คาน่า",
      "desc": "ได้รับค่า [Charge] 1 หน่วย\nได้รับค่า [Charge] 1 หน่วยทุก ๆ ครั้งที่ตัวละครนี้ผลาญจำนวน [Charge] สะสมรวม 10 หน่วยในการเผชิญหน้าครั้งนี้\n- หากตัวละครนี้สามารถรับค่า [Charge] เมื่อผลาญจำนวน [Charge] ที่ตนเองมี ได้อยู่แล้ว เอฟเฟกต์นี้จะไม่ทับซ้อนกับเอฟเฟกต์นั้น\n- สกิลโจมตีพื้นฐานของตัวละครนี้ที่ผลาญจำนวน [Charge] ได้: สร้างความเสียหายเพิ่มขึ้น +5% ตามทุก ๆ ค่า [Charge] ที่ตนเองมี (สูงสุด 25%)\n\nหากตัวละครนี้คือ 'E.G.O บริษัทโลโบโตมี:: ในนามแห่งความรักและความเกลียดชัง - ดอน กิโฮเต้' จะสามารถใช้งานสกิล 3 ได้เพิ่มเติมอีก 1 ครั้ง",
      "summary": "ช่วยการเก็บค่า [Charge]\nและทำให้สาวน้อยเวทมนตร์ดอน กิโฮเต้ใช้สกิล 3 ได้อีก 1 รอบ"
    },
    {
      "id": 2050811,
      "name": "เมโทรนอมจับจังหวะ",
      "desc": "เริ่มเทิร์น: ในเทิร์นเลขคี่ จะได้รับ [AttackDmgUp] 1 หน่วย; ในเทิร์นเลขคู่ จะได้รับ [Protection] 1 หน่วย\n- ไม่ทับซ้อนกับของขวัญ E.G.O 'เครื่องเมโทรนอมจับจังหวะ' (หากของขวัญ E.G.O ดังกล่าวมีการเสริมพลังแล้ว จะทำการหักลบปริมาณเอฟเฟกต์ดังกล่าว ด้วยปริมาณเอฟเฟกต์ที่ได้จากเอฟเฟกต์นี้)\n- จะไม่ส่งผลกับการมอบปริมาณเอฟเฟกต์ให้กับพันธมิตรคนอื่น\n\nเมื่อใช้สกิล E.G.O จะได้รับ [AccumulatedPastSinner] 1 หน่วยในเทิร์นถัดไป (มีผลหนึ่งครั้งต่อการเผชิญหน้า)\n- ได้รับ [AccumulatedPastSinner] 1 หน่วยทุกครั้งหลังจากจบเทิร์นต่อ ๆ ไป"
    }
  ]
}