{
  "dataList": [
    {
      "id": 9011001,
      "levelList": [
        {
          "level": 1,
          "name": "ผ่า",
          "desc": "",
          "coinlist": [
            {
              "coindescs": [
                {
                  "desc": "[OnSucceedAttack] สร้างค่า [Laceration] 2 หน่วย"
                }
              ]
            },
            {
              "coindescs": [
                {
                  "desc": "[OnSucceedAttack] สร้างค่า [Laceration] 2 หน่วย"
                }
              ]
            }
          ]
        }
      ]
    },
    {
      "id": 9011002,
      "levelList": [
        {
          "level": 1,
          "name": "ฟาดฟันอย่างตั้งใจ",
          "desc": "หากเป้าหมายมีค่า [Laceration] 7+ หน่วย แต้มเหรียญจะเพิ่มขึ้น +1 แต้ม\n[WinDuel] ได้รับ [SlashDamageUp] 1 หน่วยในเทิร์นถัดไป",
          "coinlist": [
            {
              "coindescs": [
                {
                  "desc": "หากเป้าหมายมี [Laceration] จะสร้างความเสียหายเพิ่มขึ้น +50%"
                },
                {
                  "desc": "[OnSucceedAttack] สร้างจำนวนครั้ง [Laceration] +2 หน่วย"
                }
              ]
            }
          ]
        }
      ]
    },
    {
      "id": 9011003,
      "levelList": [
        {
          "level": 1,
          "name": "กระจายเชิงกลม",
          "desc": "หากเป้าหมายมีค่า [Laceration] 5+ หน่วย แต้มเหรียญจะเพิ่มขึ้น +1 แต้ม\n[WinDuel] ได้รับ [SlashResultUp] 1 หน่วยในเทิร์นถัดไป",
          "coinlist": [
            {
              "coindescs": [
                {
                  "desc": "หากเป้าหมายมี [Laceration] จะสร้างความเสียหายเพิ่มขึ้น +20%"
                }
              ]
            },
            {
              "coindescs": [
                {
                  "desc": "หากเป้าหมายมี [Laceration] จะสร้างความเสียหายเพิ่มขึ้น +10%"
                }
              ]
            },
            {
              "coindescs": [
                {
                  "desc": "หากเป้าหมายมี [Laceration] จะสร้างความเสียหายเพิ่มขึ้น +40%"
                }
              ]
            }
          ]
        }
      ]
    },
    {
      "id": 9011004,
      "levelList": [
        {
          "level": 1,
          "name": "หลบหลีก",
          "desc": "[OnSucceedEvade] ได้รับ [SlashDamageUp] 1 หน่วยในเทิร์นถัดไป (มีผลเทิร์นละครั้ง)",
          "coinlist": [
            {
              "coindescs": [
                {
                  "desc": ""
                }
              ]
            }
          ]
        }
      ]
    },
    {
      "id": 9011101,
      "levelList": [
        {
          "level": 1,
          "name": "ปาด",
          "desc": "",
          "coinlist": [
            {
              "coindescs": [
                {
                  "desc": "[OnSucceedAttack] สร้างค่า [Laceration] 3 หน่วย"
                }
              ]
            }
          ]
        }
      ]
    },
    {
      "id": 9011102,
      "levelList": [
        {
          "level": 1,
          "name": "ผ่า",
          "desc": "",
          "coinlist": [
            {
              "coindescs": [
                {
                  "desc": "หากเป้าหมายมี [Laceration] จะสร้างความเสียหายเพิ่มขึ้น +30%"
                },
                {
                  "desc": "[OnSucceedAttack] สร้างจำนวนครั้ง [Laceration] +2 หน่วย"
                }
              ]
            }
          ]
        }
      ]
    },
    {
      "id": 9011103,
      "levelList": [
        {
          "level": 1,
          "name": "ฟาดฟันคมกริบ",
          "desc": "[WinDuel] ได้รับ [SlashDamageUp] 1 หน่วยในเทิร์นถัดไป",
          "coinlist": [
            {
              "coindescs": [
                {
                  "desc": "หากเป้าหมายมี [Laceration] จะสร้างความเสียหายเพิ่มขึ้น +10%"
                }
              ]
            },
            {
              "coindescs": [
                {
                  "desc": "หากเป้าหมายมี [Laceration] จะสร้างความเสียหายเพิ่มขึ้น +10%"
                }
              ]
            },
            {
              "coindescs": [
                {
                  "desc": "หากเป้าหมายมี [Laceration] จะสร้างความเสียหายเพิ่มขึ้น +20%"
                }
              ]
            }
          ]
        }
      ]
    },
    {
      "id": 9011104,
      "levelList": [
        {
          "level": 1,
          "name": "หลบหลีก",
          "desc": "[OnSucceedEvade] ได้รับ [SlashDamageUp] 1 หน่วยในเทิร์นถัดไป (มีผลเทิร์นละครั้ง)",
          "coinlist": [
            {
              "coindescs": [
                {
                  "desc": ""
                }
              ]
            }
          ]
        }
      ]
    },
    {
      "id": 9011201,
      "levelList": [
        {
          "level": 1,
          "name": "ฟันฉับลง",
          "desc": "",
          "coinlist": [
            {
              "coindescs": [
                {
                  "desc": "[OnSucceedAttack] สร้างค่า [Laceration] 3 หน่วย"
                }
              ]
            },
            {
              "coindescs": [
                {
                  "desc": "[OnSucceedAttack] สร้างค่า [Laceration] 3 หน่วย"
                }
              ]
            }
          ]
        }
      ]
    },
    {
      "id": 9011202,
      "levelList": [
        {
          "level": 1,
          "name": "ย้อนฟัน",
          "desc": "[WinDuel] สร้าง [Paralysis] 1 หน่วยในเทิร์นถัดไป",
          "coinlist": [
            {
              "coindescs": [
                {
                  "desc": "[OnSucceedAttack] สร้างค่า [Laceration] 5 หน่วย"
                }
              ]
            }
          ]
        }
      ]
    },
    {
      "id": 9011203,
      "levelList": [
        {
          "level": 1,
          "name": "ฟาดฟันอย่างตั้งใจ",
          "desc": "[WinDuel] สร้าง [Protection] 1 หน่วยในเทิร์นถัดไป",
          "coinlist": [
            {
              "coindescs": [
                {
                  "desc": "[OnSucceedAttack] สร้างค่า [Laceration] 4 หน่วย"
                }
              ]
            },
            {
              "coindescs": [
                {
                  "desc": "[OnSucceedAttack] สร้างค่า [Laceration] 4 หน่วย"
                }
              ]
            }
          ]
        }
      ]
    },
    {
      "id": 9011204,
      "levelList": [
        {
          "level": 1,
          "name": "ตั้งการ์ด",
          "desc": "[StartBattle] ได้รับ [Protection] 1 หน่วย",
          "coinlist": [
            {
              "coindescs": [
                {
                  "desc": ""
                }
              ]
            }
          ]
        }
      ]
    },
    {
      "id": 9011301,
      "levelList": [
        {
          "level": 1,
          "name": "ฟันเจาะทะลวงกาย",
          "desc": "",
          "coinlist": [
            {
              "coindescs": [
                {
                  "desc": "[OnSucceedAttack] สร้างค่า [Laceration] 2 หน่วย"
                }
              ]
            },
            {
              "coindescs": [
                {
                  "desc": "[OnSucceedAttack] สร้างค่า [Laceration] 2 หน่วย"
                }
              ]
            },
            {
              "coindescs": [
                {
                  "desc": "[OnSucceedAttack] สร้างค่า [Laceration] 2 หน่วย"
                }
              ]
            }
          ]
        }
      ]
    },
    {
      "id": 9011302,
      "levelList": [
        {
          "level": 1,
          "name": "ฟาดฟันคมกริบ",
          "desc": "หากเป้าหมายมีค่า [Laceration] 7+ หน่วย แต้มเหรียญจะเพิ่มขึ้น +1 แต้ม\n[WinDuel] ได้รับ [Protection] 1 หน่วยในเทิร์นถัดไป",
          "coinlist": [
            {
              "coindescs": [
                {
                  "desc": "[OnSucceedAttack] สร้างจำนวนครั้ง [Laceration] +3 หน่วย"
                },
                {
                  "desc": "[OnSucceedAttack] สร้าง [Paralysis] 1 หน่วยในเทิร์นถัดไป"
                }
              ]
            }
          ]
        }
      ]
    },
    {
      "id": 9011303,
      "levelList": [
        {
          "level": 1,
          "name": "ฟาดฟันอย่างตั้งใจ",
          "desc": "หากเป้าหมายมีค่า [Laceration] 5+ หน่วย แต้มเหรียญจะเพิ่มขึ้น +1 แต้ม\n[StartBattle] ได้รับ [Protection] 1 หน่วย\n[WinDuel] ได้รับ [Protection] 1 หน่วยในเทิร์นถัดไป",
          "coinlist": [
            {
              "coindescs": [
                {
                  "desc": "[OnSucceedAttack] สร้างจำนวนครั้ง [Laceration] +2 หน่วย"
                }
              ]
            },
            {
              "coindescs": [
                {
                  "desc": "[OnSucceedAttack] สร้างจำนวนครั้ง [Laceration] +2 หน่วย"
                }
              ]
            }
          ]
        }
      ]
    },
    {
      "id": 9011304,
      "levelList": [
        {
          "level": 1,
          "name": "ตั้งการ์ด",
          "desc": "[StartBattle] ได้รับ [Protection] 2 หน่วย",
          "coinlist": [
            {
              "coindescs": [
                {
                  "desc": ""
                }
              ]
            }
          ]
        }
      ]
    },
    {
      "id": 9101301,
      "levelList": [
        {
          "level": 1,
          "name": "เงาเมฆา",
          "desc": "[WhenUse] หากเป้าหมายมี [Laceration] จะสร้างความเสียหายเพิ่มขึ้น +10%",
          "coinlist": [
            {
              "coindescs": [
                {
                  "desc": "[OnSucceedAttack] สร้างค่า [Laceration] 4 หน่วย และจำนวนครั้ง [Laceration] +1 หน่วย"
                }
              ]
            },
            {
              "coindescs": [
                {
                  "desc": "[OnSucceedAttack] สร้างค่า [Laceration] 4 หน่วย และจำนวนครั้ง [Laceration] +1 หน่วย"
                }
              ]
            }
          ]
        }
      ]
    },
    {
      "id": 9101302,
      "levelList": [
        {
          "level": 1,
          "name": "เก็บกวาด",
          "desc": "หากเป้าหมายมีค่า [Laceration] 5+ หน่วย แต้มเหรียญจะเพิ่มขึ้น +1 แต้ม",
          "coinlist": [
            {
              "coindescs": [
                {
                  "desc": "[OnSucceedAttack] สร้าง [SlashTakeDamageUp] 1 หน่วยในเทิร์นถัดไป"
                },
                {
                  "desc": "[OnSucceedAttackHead] สร้างค่า [Laceration] 1 หน่วย"
                }
              ]
            },
            {
              "coindescs": [
                {
                  "desc": "[OnSucceedAttack] สร้าง [SlashTakeDamageUp] 1 หน่วยในเทิร์นถัดไป"
                },
                {
                  "desc": "[OnSucceedAttackHead] สร้างค่า [Laceration] 1 หน่วย"
                }
              ]
            }
          ]
        }
      ]
    },
    {
      "id": 9101303,
      "levelList": [
        {
          "level": 1,
          "name": "ตวัดดาบทรงกลม",
          "desc": "หากเป้าหมายมีค่า [Laceration] 5+ หน่วย แต้มเหรียญจะเพิ่มขึ้น +1 แต้ม",
          "coinlist": [
            {
              "coindescs": [
                {
                  "desc": "[OnSucceedAttack] สร้าง [Paralysis] 1 หน่วยในเทิร์นถัดไป"
                }
              ]
            },
            {
              "coindescs": [
                {
                  "desc": "[OnSucceedAttack] สร้างค่า [Laceration] 8 หน่วย"
                }
              ]
            },
            {
              "coindescs": [
                {
                  "desc": "[OnSucceedAttack] สร้างจำนวนครั้ง [Laceration] +3 หน่วย"
                }
              ]
            }
          ]
        }
      ]
    },
    {
      "id": 9101304,
      "levelList": [
        {
          "level": 1,
          "name": "คมแหลม",
          "desc": "[StartBattle] มอบ [SlashDamageUp] 2 หน่วยให้กับพันธมิตรทั้งหมด (รวมถึงตัวละครนี้)\n[StartBattle] ได้รับ [SlashResultUp] 2 หน่วย",
          "coinlist": [
            {},
            {
              "coindescs": [
                {
                  "desc": "[OnSucceedAttack] สร้างค่า [Laceration] 2 หน่วย"
                }
              ]
            }
          ]
        }
      ]
    },
    {
      "id": 9101305,
      "levelList": [
        {
          "level": 1,
          "name": "ดาบตัดผ่านภา",
          "desc": "[StartBattle] หากเป้าหมายหลักมีค่า [Laceration] 10+ หน่วย น้ำหนักการโจมตีจะเพิ่มขึ้น +1 ช่อง\n[StartBattle] หากตัวละครนี้เตรียมจะได้ใช้สกิลโจมตี 5+ สกิลในเทิร์นนี้ แต้มปิดท้ายสกิลจะเพิ่มขึ้น +5 แต้ม\n[WinDuel] พันธมิตรทั้งหมดฟื้นฟู SP 10 หน่วย\nหากเป้าหมายมีค่า [Laceration] 7+ หน่วย จะสร้างความเสียหายเพิ่มขึ้น +30%",
          "coinlist": [
            {
              "coindescs": [
                {
                  "desc": "[OnSucceedAttackHead] สร้างค่า [Laceration] 2 หน่วย"
                }
              ]
            },
            {
              "coindescs": [
                {
                  "desc": "[OnSucceedAttackHead] สร้างค่า [Laceration] 3 หน่วย"
                }
              ]
            },
            {
              "coindescs": [
                {
                  "desc": "หากเป้าหมายมีค่า [Laceration] 7+ หน่วย จะสร้างความเสียหายเพิ่มขึ้น +50%"
                },
                {
                  "desc": "[OnSucceedAttack] สร้างจำนวนครั้ง [Laceration] +10 หน่วย"
                }
              ]
            }
          ]
        }
      ]
    },
    {
      "id": 9101306,
      "levelList": [
        {
          "level": 1,
          "name": "กฎแห่งแบ็คสตรีทส์",
          "desc": "[WhenUse] เพิ่มเหรียญสกิลนี้ขึ้นอีก +1 เหรียญ ตามทุก ๆ พันธมิตรอื่นที่ยังรอดชีวิต (สูงสุด 3 เหรียญ)",
          "coinlist": [
            {
              "coindescs": [
                {
                  "desc": "[OnSucceedAttack] สร้างจำนวนครั้ง [Laceration] +2 หน่วย"
                },
                {
                  "desc": "[EnemyKill] พันธมิตรทั้งหมดฟื้นฟู SP 20 หน่วย"
                }
              ]
            }
          ]
        }
      ]
    }
  ]
}