{
  "dataList": [
    {
      "id": 9018301,
      "levelList": [
        {
          "level": 1,
          "name": "Unmannerly Attack",
          "desc": "[WhenUse] ได้รับ 1 [Agility] ในเทิร์นถัดไป",
          "coinlist": [
            {
              "coindescs": [
                {
                  "desc": "[OnSucceedAttack] สร้าง +2 [Laceration] จำนวนครั้ง"
                }
              ]
            }
          ]
        }
      ]
    },
    {
      "id": 9018302,
      "levelList": [
        {
          "level": 1,
          "name": "Tendon Slice",
          "desc": "[WhenUse] If this unit's Speed is faster than the target's, แต้มเหรียญ +1\n[WhenUse] หากเป้าหมายมี 3+ [Laceration], แต้มเริ่มต้นสกิล +1",
          "coinlist": [
            {
              "coindescs": [
                {
                  "desc": "[OnSucceedAttack] สร้าง 2 [Laceration]"
                }
              ]
            },
            {
              "coindescs": [
                {
                  "desc": "[OnSucceedAttack] สร้าง 2 [Laceration]"
                },
                {
                  "desc": "[OnSucceedAttack] สร้าง 2 [Binding] ในเทิร์นถัดไป"
                }
              ]
            }
          ]
        }
      ]
    },
    {
      "id": 9018303,
      "levelList": [
        {
          "level": 1,
          "name": "Messy Attack",
          "desc": "[WhenUse] At 7+ Speed, แต้มเหรียญ +1\n[WhenUse] หากเป้าหมายมี 4+ [Laceration], แต้มเหรียญ +1\n[WinDuel] Deal more damage based on Clash count (+5% per Clash count, max 50%)\n[WinDuel] สร้าง +3 [Laceration] จำนวนครั้ง",
          "coinlist": [
            {
              "coindescs": [
                {
                  "desc": "[OnSucceedAttack] สร้าง 2 [Laceration]"
                }
              ]
            },
            {
              "coindescs": [
                {
                  "desc": "[OnSucceedAttack] สร้าง 2 [Laceration]"
                }
              ]
            }
          ]
        }
      ]
    },
    {
      "id": 9018304,
      "levelList": [
        {
          "level": 1,
          "name": "ตั้งการ์ด",
          "desc": "[WhenUse] ได้รับ 3 Shield ตามทุก ๆ type of negative effect on self (สูงสุด 10)",
          "coinlist": [
            {
              "coindescs": [
                {
                  "desc": ""
                }
              ]
            }
          ]
        }
      ]
    },
    {
      "id": 9018401,
      "levelList": [
        {
          "level": 1,
          "name": "Cleave",
          "desc": "",
          "coinlist": [
            {
              "coindescs": [
                {
                  "desc": "[OnSucceedAttack] สร้าง +2 [Laceration] จำนวนครั้ง"
                }
              ]
            }
          ]
        }
      ]
    },
    {
      "id": 9018402,
      "levelList": [
        {
          "level": 1,
          "name": "Leg Wound",
          "desc": "[WhenUse] แต้มเหรียญ +1 ตามทุก ๆ 3 [Laceration] บนตัวเป้าหมาย (สูงสุด 2)",
          "coinlist": [
            {
              "coindescs": [
                {
                  "desc": "[OnSucceedAttack] สร้าง 2 [Laceration]"
                }
              ]
            },
            {
              "coindescs": [
                {
                  "desc": "[OnSucceedAttack] สร้าง 2 [Laceration]"
                },
                {
                  "desc": "[OnSucceedAttack] สร้าง 1 [Paralysis] ในเทิร์นถัดไป"
                }
              ]
            }
          ]
        }
      ]
    },
    {
      "id": 9018403,
      "levelList": [
        {
          "level": 1,
          "name": "Wild Swipe",
          "desc": "[WhenUse] แต้มเหรียญ +1 ตามทุก ๆ 3 [Laceration] บนตัวเป้าหมาย (สูงสุด 2)",
          "coinlist": [
            {
              "coindescs": [
                {
                  "desc": "[OnSucceedAttack] สร้าง 2 [Laceration]"
                }
              ]
            },
            {
              "coindescs": [
                {
                  "desc": "[OnSucceedAttack] สร้าง 2 [Laceration]"
                }
              ]
            }
          ]
        }
      ]
    },
    {
      "id": 9018404,
      "levelList": [
        {
          "level": 1,
          "name": "สวนกลับ",
          "desc": "[BeforeHit] ได้รับ 2 Shield ตามทุก ๆ type of negative effect on self (สูงสุด 10)",
          "coinlist": [
            {
              "coindescs": [
                {
                  "desc": "[OnSucceedAttack] If this unit has Shield, สร้าง 1 [Paralysis] บนตัวเป้าหมาย ในเทิร์นถัดไป"
                }
              ]
            }
          ]
        }
      ]
    },
    {
      "id": 9018701,
      "levelList": [
        {
          "level": 1,
          "name": "Extract Fuel",
          "desc": "หากเป้าหมายมี 2+ [Laceration], แต้มเหรียญ +1",
          "coinlist": [
            {
              "coindescs": [
                {
                  "desc": "[OnSucceedAttack] สร้าง 2 [Laceration]"
                }
              ]
            },
            {
              "coindescs": [
                {
                  "desc": "[OnSucceedAttack] สร้าง +2 [Laceration] จำนวนครั้ง"
                },
                {
                  "desc": "[OnSucceedAttack] Heal 2 HP"
                }
              ]
            }
          ]
        }
      ]
    },
    {
      "id": 9018702,
      "levelList": [
        {
          "level": 1,
          "name": "Sweep the Backstreets",
          "desc": "หากเป้าหมายมี 2+ [Laceration], แต้มเหรียญ +1",
          "coinlist": [
            {
              "coindescs": [
                {
                  "desc": "[OnSucceedAttack] สร้าง 2 [Paralysis]"
                }
              ]
            },
            {
              "coindescs": [
                {
                  "desc": "[OnSucceedAttack] สร้าง 2 [Laceration]"
                }
              ]
            }
          ]
        }
      ]
    },
    {
      "id": 9018703,
      "levelList": [
        {
          "level": 1,
          "name": "Trash Disposal",
          "desc": "หากเป้าหมายมี 4+ [Laceration], แต้มเหรียญ +1",
          "coinlist": [
            {
              "coindescs": [
                {
                  "desc": "[OnSucceedAttack] สร้าง 4 [Laceration]"
                }
              ]
            },
            {
              "coindescs": [
                {
                  "desc": "[SuperCoin]"
                },
                {
                  "desc": "[OnSucceedAttack] สร้าง +1 [Laceration] จำนวนครั้ง"
                },
                {
                  "desc": "On Hit with this Coin, heal 30% of the HP damage dealt"
                },
                {
                  "desc": "[OnSucceedAttackHead] Reuse this Coin (3 times per Skill)"
                }
              ]
            }
          ]
        }
      ]
    },
    {
      "id": 9018704,
      "levelList": [
        {
          "level": 1,
          "name": "333..1973",
          "desc": "[StartBattle] ได้รับ 4 [Persistent]",
          "coinlist": [
            {
              "coindescs": [
                {
                  "desc": "[SuperCoin]"
                },
                {
                  "desc": "[OnSucceedAttack] Lower user's Stagger Threshold by 5"
                }
              ]
            },
            {
              "coindescs": [
                {
                  "desc": "[SuperCoin]"
                },
                {
                  "desc": "[OnSucceedAttack] สร้าง +3 Bleed จำนวนครั้ง"
                }
              ]
            }
          ]
        }
      ]
    },
    {
      "id": 9018705,
      "levelList": [
        {
          "level": 1,
          "name": "For the Family",
          "desc": "[StartBattle] มอบ 1 [Protection] to 2 random allies",
          "coinlist": [
            {
              "coindescs": [
                {
                  "desc": ""
                }
              ]
            }
          ]
        }
      ]
    },
    {
      "id": 9018706,
      "levelList": [
        {
          "level": 1,
          "name": "Night in the Backstreets",
          "desc": "หากเป้าหมายมี 2+ [Laceration], แต้มเหรียญ +1",
          "coinlist": [
            {
              "coindescs": [
                {
                  "desc": "[OnSucceedAttack] Heal 8 HP"
                },
                {
                  "desc": "[OnSucceedAttack] สร้าง +2 [Laceration] จำนวนครั้ง"
                }
              ]
            },
            {
              "coindescs": [
                {
                  "desc": "[SuperCoin]"
                },
                {
                  "desc": "[OnSucceedAttack] Heal 8 HP"
                },
                {
                  "desc": "[OnSucceedAttack] Lower user's Stagger Threshold by 8"
                },
                {
                  "desc": "[OnSucceedAttack] Activate [Laceration] on the target once (reduce [Laceration] จำนวนครั้ง by 1)"
                }
              ]
            }
          ]
        }
      ]
    },
    {
      "id": 9019301,
      "levelList": [
        {
          "level": 1,
          "name": "Sudden Strike",
          "desc": "[WhenUse] ได้รับ 1 [Agility] ในเทิร์นถัดไป",
          "coinlist": [
            {
              "coindescs": [
                {
                  "desc": "[OnSucceedAttack] สร้าง 3 [Laceration]"
                }
              ]
            }
          ]
        }
      ]
    },
    {
      "id": 9019302,
      "levelList": [
        {
          "level": 1,
          "name": "Muscle Slice",
          "desc": "[WhenUse] If this unit's Speed is faster than the target's, แต้มเหรียญ +1\n[WhenUse] หากเป้าหมายมี 3+ [Laceration], แต้มเริ่มต้นสกิล +1",
          "coinlist": [
            {
              "coindescs": [
                {
                  "desc": "[OnSucceedAttack] สร้าง +2 [Laceration] จำนวนครั้ง"
                }
              ]
            },
            {
              "coindescs": [
                {
                  "desc": "[OnSucceedAttack] สร้าง +2 [Laceration] จำนวนครั้ง"
                },
                {
                  "desc": "[OnSucceedAttack] สร้าง 2 [Binding] ในเทิร์นถัดไป"
                }
              ]
            }
          ]
        }
      ]
    },
    {
      "id": 9019303,
      "levelList": [
        {
          "level": 1,
          "name": "Indiscriminate Attack",
          "desc": "[WhenUse] At 7+ Speed, แต้มเหรียญ +1\n[WhenUse] หากเป้าหมายมี 4+ [Laceration], แต้มเหรียญ +1\n[WinDuel] Deal more damage based on Clash count (+5% per Clash count, max 50%)\n[WinDuel] สร้าง 5 [Laceration]",
          "coinlist": [
            {
              "coindescs": [
                {
                  "desc": "[OnSucceedAttack] สร้าง +2 [Laceration] จำนวนครั้ง"
                }
              ]
            },
            {
              "coindescs": [
                {
                  "desc": "[OnSucceedAttack] สร้าง +2 [Laceration] จำนวนครั้ง"
                }
              ]
            }
          ]
        }
      ]
    },
    {
      "id": 9019304,
      "levelList": [
        {
          "level": 1,
          "name": "ตั้งการ์ด",
          "desc": "[WhenUse] ได้รับ 3 Shield ตามทุก ๆ type of negative effect on self (สูงสุด 10)",
          "coinlist": [
            {
              "coindescs": [
                {
                  "desc": ""
                }
              ]
            }
          ]
        }
      ]
    },
    {
      "id": 9019401,
      "levelList": [
        {
          "level": 1,
          "name": "Slice",
          "desc": "",
          "coinlist": [
            {
              "coindescs": [
                {
                  "desc": "[OnSucceedAttack] สร้าง 3 [Laceration]"
                }
              ]
            }
          ]
        }
      ]
    },
    {
      "id": 9019402,
      "levelList": [
        {
          "level": 1,
          "name": "Muscle Wound",
          "desc": "[WhenUse] แต้มเหรียญ +1 ตามทุก ๆ 3 [Laceration] บนตัวเป้าหมาย (สูงสุด 2)",
          "coinlist": [
            {
              "coindescs": [
                {
                  "desc": "[OnSucceedAttack] สร้าง +2 [Laceration] จำนวนครั้ง"
                }
              ]
            },
            {
              "coindescs": [
                {
                  "desc": "[OnSucceedAttack] สร้าง +2 [Laceration] จำนวนครั้ง"
                },
                {
                  "desc": "[OnSucceedAttack] สร้าง 1 [Paralysis] ในเทิร์นถัดไป"
                }
              ]
            }
          ]
        }
      ]
    },
    {
      "id": 9019403,
      "levelList": [
        {
          "level": 1,
          "name": "Swift Attack",
          "desc": "[WhenUse] แต้มเหรียญ +1 ตามทุก ๆ 3 [Laceration] บนตัวเป้าหมาย (สูงสุด 2)",
          "coinlist": [
            {
              "coindescs": [
                {
                  "desc": "[OnSucceedAttack] สร้าง +2 [Laceration] จำนวนครั้ง"
                }
              ]
            },
            {
              "coindescs": [
                {
                  "desc": "[OnSucceedAttack] สร้าง +2 [Laceration] จำนวนครั้ง"
                }
              ]
            }
          ]
        }
      ]
    },
    {
      "id": 9019404,
      "levelList": [
        {
          "level": 1,
          "name": "สวนกลับ",
          "desc": "[BeforeHit] ได้รับ 2 Shield ตามทุก ๆ type of negative effect on self (สูงสุด 10)",
          "coinlist": [
            {
              "coindescs": [
                {
                  "desc": "[OnSucceedAttack] If this unit has Shield, สร้าง 1 [Paralysis] บนตัวเป้าหมาย ในเทิร์นถัดไป"
                }
              ]
            }
          ]
        }
      ]
    },
    {
      "id": 9018501,
      "levelList": [
        {
          "level": 1,
          "name": "Startling Strike",
          "desc": "[WhenUse] หากเป้าหมายมี 3+ [Burst], แต้มแคลชสกิล +1",
          "coinlist": [
            {
              "coindescs": [
                {
                  "desc": "[OnSucceedAttack] สร้าง +2 [Burst] จำนวนครั้ง"
                }
              ]
            }
          ]
        }
      ]
    },
    {
      "id": 9018502,
      "levelList": [
        {
          "level": 1,
          "name": "Restraint",
          "desc": "",
          "coinlist": [
            {
              "coindescs": [
                {
                  "desc": "[OnSucceedAttack] สร้าง 2 [Burst]"
                }
              ]
            },
            {
              "coindescs": [
                {
                  "desc": "[SuperCoin]"
                },
                {
                  "desc": "[OnSucceedAttack] สร้าง 2 [Burst]"
                },
                {
                  "desc": "[UnBrokenCoinOnSucceedAttack] Reuse this Coin (this unit's Speed / 4) times (สูงสุด 2)"
                }
              ]
            }
          ]
        }
      ]
    },
    {
      "id": 9018503,
      "levelList": [
        {
          "level": 1,
          "name": "Feather Strike",
          "desc": "If this unit's Speed is faster than the target's ได้รับ แต้มเหรียญ based on Speed difference (แต้มเหรียญ +1 ตามทุก ๆ 2 Speed difference; max 3)\n[WhenUse] หากเป้าหมายมี 4+ [Burst], แต้มเหรียญ +1\n[WinDuel] สร้าง +3 [Burst] จำนวนครั้ง",
          "coinlist": [
            {
              "coindescs": [
                {
                  "desc": "[OnSucceedAttack] สร้าง +1 [Burst] จำนวนครั้ง"
                }
              ]
            },
            {
              "coindescs": [
                {
                  "desc": "[OnSucceedAttack] สร้าง 2 [Burst]"
                },
                {
                  "desc": "[OnSucceedAttack] สร้าง [BurstAgility]"
                }
              ]
            },
            {
              "coindescs": [
                {
                  "desc": "[SuperCoin]"
                },
                {
                  "desc": "หากเป้าหมายมี [BurstAgility], deal +50% damage"
                },
                {
                  "desc": "[OnSucceedAttack] ได้รับ 3 [LegStrength]"
                }
              ]
            }
          ]
        }
      ]
    },
    {
      "id": 9018504,
      "levelList": [
        {
          "level": 1,
          "name": "The Windup",
          "desc": "[DuelCounter] \n[WinDuel] ได้รับ 3 [Agility] ในเทิร์นถัดไป",
          "coinlist": [
            {}
          ]
        }
      ]
    },
    {
      "id": 9018601,
      "levelList": [
        {
          "level": 1,
          "name": "Pursuit",
          "desc": "[WhenUse] หากเป้าหมายมี 3+ [Burst], แต้มแคลชสกิล +1",
          "coinlist": [
            {
              "coindescs": [
                {
                  "desc": "[OnSucceedAttack] สร้าง 2 [Burst]"
                }
              ]
            }
          ]
        }
      ]
    },
    {
      "id": 9018602,
      "levelList": [
        {
          "level": 1,
          "name": "Overwhelm",
          "desc": "",
          "coinlist": [
            {
              "coindescs": [
                {
                  "desc": "[OnSucceedAttack] สร้าง +2 [Burst] จำนวนครั้ง"
                }
              ]
            },
            {
              "coindescs": [
                {
                  "desc": "[SuperCoin]"
                },
                {
                  "desc": "[OnSucceedAttack] สร้าง 2 [Burst]"
                },
                {
                  "desc": "[UnBrokenCoinOnSucceedAttack] Reuse this Coin (this unit's Speed / 4) times (สูงสุด 2)"
                }
              ]
            }
          ]
        }
      ]
    },
    {
      "id": 9018603,
      "levelList": [
        {
          "level": 1,
          "name": "Umbra Strike",
          "desc": "If this unit's Speed is faster than the target's ได้รับ แต้มเหรียญ based on Speed difference (แต้มเหรียญ +1 ตามทุก ๆ 2 Speed difference; max 3)\n[WhenUse] หากเป้าหมายมี 4+ [Burst], แต้มเหรียญ +1\n[WinDuel] สร้าง +3 [Burst] จำนวนครั้ง",
          "coinlist": [
            {
              "coindescs": [
                {
                  "desc": "[OnSucceedAttack] สร้าง +3 [Burst] จำนวนครั้ง"
                }
              ]
            },
            {
              "coindescs": [
                {
                  "desc": "[OnSucceedAttack] สร้าง 1 [Burst]"
                },
                {
                  "desc": "[OnSucceedAttack] สร้าง [BurstAgility]"
                }
              ]
            },
            {
              "coindescs": [
                {
                  "desc": "[SuperCoin]"
                },
                {
                  "desc": "หากเป้าหมายมี [BurstAgility], deal +50% damage"
                },
                {
                  "desc": "[OnSucceedAttack] ได้รับ 3 [LegStrength]"
                }
              ]
            }
          ]
        }
      ]
    },
    {
      "id": 9018604,
      "levelList": [
        {
          "level": 1,
          "name": "The Windup",
          "desc": "[DuelCounter] \n[WinDuel] ได้รับ 3 [Agility] ในเทิร์นถัดไป",
          "coinlist": [
            {}
          ]
        }
      ]
    },
    {
      "id": 9102001,
      "levelList": [
        {
          "level": 1,
          "name": "Aim for the Solar Plexus",
          "desc": "",
          "coinlist": [
            {
              "coindescs": [
                {
                  "desc": "[OnSucceedAttack] สร้าง 1 [Paralysis] ในเทิร์นถัดไป"
                }
              ]
            }
          ]
        }
      ]
    },
    {
      "id": 9102002,
      "levelList": [
        {
          "level": 1,
          "name": "Right in the Dome",
          "desc": "[WhenUse] หากเป้าหมายมี [MiddleFingerBook], สร้าง 2 additional [DefenseDown] with this Skill",
          "coinlist": [
            {
              "coindescs": [
                {
                  "desc": "[OnSucceedAttack] สร้าง 1 [Binding] ในเทิร์นถัดไป"
                },
                {
                  "desc": "[OnSucceedAttack] สร้าง 2 [DefenseDown] ในเทิร์นถัดไป"
                }
              ]
            }
          ]
        }
      ]
    },
    {
      "id": 9102003,
      "levelList": [
        {
          "level": 1,
          "name": "Gut Crush",
          "desc": "[WhenUse] หากเป้าหมายมี [MiddleFingerBook], สร้าง 1 additional [AttackDown] with this Skill",
          "coinlist": [
            {
              "coindescs": [
                {
                  "desc": "[OnSucceedAttackHead] สร้าง 1 [AttackDown] ในเทิร์นถัดไป"
                },
                {
                  "desc": "[OnSucceedAttack] หากเป้าหมายมี [MiddleFingerBook], ได้รับ 1 [PlusCoinValueUp] ในเทิร์นถัดไป"
                }
              ]
            },
            {
              "coindescs": [
                {
                  "desc": "[OnSucceedAttackHead] สร้าง 1 [AttackDown] ในเทิร์นถัดไป"
                },
                {
                  "desc": "[OnSucceedAttack] หากเป้าหมายมี [MiddleFingerBook], ได้รับ 1 [PlusCoinValueUp] ในเทิร์นถัดไป"
                }
              ]
            }
          ]
        }
      ]
    },
    {
      "id": 9102004,
      "levelList": [
        {
          "level": 1,
          "name": "Vengeance awaits you all!",
          "desc": "Deal +10% damage ตามทุก ๆ 2 [MiddleFingerBook] on the target (สูงสุด 50%)\n[BeforeAttack] At 40% or less HP, ได้รับ Atk Weight +1\n[WhenUse] If the main target has [MiddleFingerBook], convert all Coins on this Skill to [SuperCoin]s\n[WhenUse] แต้มเหรียญ +1 ตามทุก ๆ 3 enemy with [MiddleFingerBook] (สูงสุด 2)\n[WhenUse] แต้มแคลชสกิล +1 ตามทุก ๆ 2 [MiddleFingerBook] on the main target (สูงสุด 5)\n[EndSkill] If this unit killed a target with [MiddleFingerBook], ได้รับ 1 [PlusCoinValueUp] ในเทิร์นถัดไป (2 times per turn)\n[EndSkill] Remove [MiddleFingerBook] on all targets that were hit",
          "coinlist": [
            {
              "coindescs": [
                {
                  "desc": "[OnSucceedAttack] สร้าง 3 [Paralysis] ในเทิร์นถัดไป"
                }
              ]
            },
            {
              "coindescs": [
                {
                  "desc": "[OnSucceedAttack] สร้าง 3 [Binding] ในเทิร์นถัดไป"
                }
              ]
            },
            {
              "coindescs": [
                {
                  "desc": "[OnSucceedAttack] สร้าง 2 [Reduction] ในเทิร์นถัดไป"
                }
              ]
            }
          ]
        }
      ]
    },
    {
      "id": 9102005,
      "levelList": [
        {
          "level": 1,
          "name": "Seize ya Chance",
          "desc": "[BeforeHit] ได้รับ 5 Shield ตามทุก ๆ [MiddleFingerBook] on the target (once per turn; max 50)\n[WhenUse] หากเป้าหมายมี 5+ [MiddleFingerBook], แต้มเริ่มต้นสกิล +3; สร้าง 4 [DefenseDown]",
          "coinlist": [
            {
              "coindescs": [
                {
                  "desc": "[OnSucceedAttack] Raise Stagger Threshold by 20"
                },
                {
                  "desc": "[OnSucceedAttack] Deal 15 fixed HP damage"
                }
              ]
            },
            {
              "coindescs": [
                {
                  "desc": "[OnSucceedAttack] Raise Stagger Threshold by 20"
                },
                {
                  "desc": "[OnSucceedAttack] Deal 15 fixed HP damage"
                }
              ]
            }
          ]
        }
      ]
    }
  ]
}