{
    "dataList": [
        {
            "id": 0,
            "place": "สันนิบาตทั้งเก้าอันอับเฉา",
            "model": "이스마엘",
            "content": "นั่นมันเครื่องเผาแนวคิดไม่ใช่เหรอ?"
        },
        {
            "id": 1,
            "model": "이스마엘",
            "content": "มันมาทำอะไรที่นี่กัน..."
        },
        {
            "id": 2,
            "model": "오티스",
            "content": "เราได้รับประกาศจากทางการว่าการชุมนุมเพื่อการประดิษฐ์เทคโนโลยีที่ไม่ได้ลงทะเบียนว่าเป็นธุรกิจ\nโดยมีสมาชิกห้าคนขึ้นไปนั้นต้องได้รับการอนุญาตจากทาง T คอร์ปเสียก่อน"
        },
        {
            "id": 3,
            "model": "오티스",
            "content": "เทคโนโลยีก็ด้วยเช่นกัน ทุกสิ่งที่ไม่ได้รับการอนุญาตจากหน่วยงานเทคโนโลยีของ T คอร์ปจะถูกยึด"
        },
        {
            "id": 4,
            "model": "오티스",
            "content": "ไม่ว่าพวกมันจะถูกลงทะเบียนหรือถูกยึดไป... พวกมันจะต้องถูกนำไปใช้ในวิธีการที่เราไม่ชอบอย่างแน่นอน"
        },
        {
            "id": 5,
            "model": "오티스",
            "content": "ก่อนที่เรื่องจะเป็นเช่นนั้น เราก็ต้องทำลายมันก่อนที่จะสายเกินไป"
        },
        {
            "id": 6,
            "model": "이스마엘",
            "content": "ไม่สิ ทำไมต้องเป็นตอนนี้ด้วย? เป็นเพราะการชุมนุมของสันนิบาตงั้นเหรอ... ไม่สิ นี่เกี่ยวกับหน้าต่างใช่ไหม...?"
        },
        {
            "id": 7,
            "model": "동랑",
            "teller": "ทงรัง",
            "title": "แผนกพัฒนาทรัพยากรอาหารของ K คอร์ป",
            "content": "เดี๋ยวก่อนนะ เดี๋ยวก่อน ความคิดที่ว่าเราต้องประดิษฐ์เทคโนโลยีอย่างลับๆ นี่มันขุดหลุมฝังตัวเองชัดๆ เลยไม่ใช่เหรอ? ใครจะไปรู้ T คอร์ปอาจจะให้การอนุมัติเราก็ได้"
        },
        {
            "id": 8,
            "model": "오티스",
            "content": "เป็นคำถามที่โง่เง่าเสียจริง นี่นายลืมไปแล้วรึยังไงว่าสันนิบาตทั้งเก้าถูกก่อตั้งขึ้นเพื่ออะไร? เรามารวมตัวเพื่อเพียงเพราะการแสวงหาความรู้ใหม่ๆ ไม่ใช่เพื่อรับใช้ปีกเหมือนล่ออับเฉา"
        },
        {
            "id": 9,
            "model": "오티스",
            "content": "เราทอดทิ้งบ้านเกิดเมืองนอนของพวกเราก็เพื่อการณ์นี้ ทีนี้นายจะบอกให้เรายอมมอบความรู้ของพวกแต่โดยดีอย่างนั้นเหรอ? ง่ายๆ แค่นั้นเลย?"
        },
        {
            "id": 10,
            "model": "동랑",
            "teller": "ทงรัง",
            "title": "แผนกพัฒนาทรัพยากรอาหารของ K คอร์ป",
            "content": "ลองมองภาพรวมดูสิ แทนที่จะเป็นแค่ T คอร์ป แต่ทั้งตัวของนครเองก็จะได้รับผลประโยชน์จากมันด้วยไม่ใช่รึไง?"
        },
        {
            "id": 11,
            "model": "동랑",
            "teller": "ทงรัง",
            "title": "แผนกพัฒนาทรัพยากรอาหารของ K คอร์ป",
            "content": "เทคโนโลยีน่ะจะมีค่าก็ต่อเมื่อใช้มันเพื่อประโยชน์ของผู้อื่นเท่านั้น หากใช้ไม่ได้ มันก็เป็นแค่ของเล่นเด็ก"
        },
        {
            "id": 12,
            "model": "동랑",
            "teller": "ทงรัง",
            "title": "แผนกพัฒนาทรัพยากรอาหารของ K คอร์ป",
            "content": "ด้วยเทคโนโลยีรักษาที่ฉันคิดค้นขึ้น ฉันอาจจะสามารถช่วยชีวิตคนเป็นร้อยๆ คนในตัวนครได้"
        },
        {
            "id": 13,
            "model": "동랑",
            "teller": "ทงรัง",
            "title": "แผนกพัฒนาทรัพยากรอาหารของ K คอร์ป",
            "content": "และเพราะแบบนั้นฉันต้องทอดทิ้งมัน... เพื่อปกป้องเจ้าสันนิบาตทั้งเก้าที่ไม่มีอยู่จริงนี้ด้วยเลยเหรอ?"
        },
        {
            "id": 14,
            "model": "과거동백",
            "teller": "ทงแบ็ค",
            "title": "สันนิบาตทั้งเก้า",
            "content": "ทงรัง ถ้าไม่ได้คิดที่จะช่วยคนทุกคนในนครล่ะก็ อย่ามาพยายามสองจิตสองใจแบบนี้เลย"
        },
        {
            "id": 15,
            "model": "과거동백",
            "teller": "ทงแบ็ค",
            "title": "สันนิบาตทั้งเก้า",
            "content": "ถ้าฉันรู้ว่าเจ้าเทคโนโลยีกระจิ้กกระจ้อยร้อยนี้สามารถช่วยทุกคนได้ล่ะก็ ฉันก็คงทุ่มสุดใจให้มันไปแล้ว"
        },
        {
            "id": 16,
            "model": "과거동백",
            "teller": "ทงแบ็ค",
            "title": "สันนิบาตทั้งเก้า",
            "content": "แต่ว่า... นายคิดว่ามันจะเปลี่ยนแปลงอะไรได้เหรอ? โลกน่ะยังไงมันก็ยังคงเละเทะอยู่ดี"
        },
        {
            "id": 17,
            "model": "동랑",
            "teller": "ทงรัง",
            "title": "แผนกพัฒนาทรัพยากรอาหารของ K คอร์ป",
            "content": "……"
        },
        {
            "id": 18,
            "model": "동랑",
            "teller": "ทงรัง",
            "title": "แผนกพัฒนาทรัพยากรอาหารของ K คอร์ป",
            "content": "นั่นสินะ ฉันผิดเอง ทั้งหมดนี่มันเพื่ออะไรกัน"
        },
        {
            "id": 19,
            "model": "동랑",
            "teller": "ทงรัง",
            "title": "แผนกพัฒนาทรัพยากรอาหารของ K คอร์ป",
            "content": "ว้าว... เครื่องเผานี่... มันเผาของได้ดีไปเลยไม่ใช่รึไง คิดว่าคนที่คิดค้นมันขึ้นมาเป็นนักวิจัยที่หลงใหลในความรู้เหมือนกันกับพวกเราไหมนะ?"
        },
        {
            "id": 20
        },
        {
            "id": 21,
            "model": "이상",
            "content": "ทงรัง... แน่หรือว่าท่านมิเป็นอันใด?"
        },
        {
            "id": 22,
            "model": "동랑",
            "teller": "ทงรัง",
            "title": "แผนกพัฒนาทรัพยากรอาหารของ K คอร์ป",
            "content": "อ้า ดูนี่สิ อีซัง"
        },
        {
            "id": 23,
            "model": "동랑",
            "teller": "ทงรัง",
            "title": "แผนกพัฒนาทรัพยากรอาหารของ K คอร์ป",
            "content": "ฉันไปพบกับของที่น่าสนใจที่แบ็คสตรีทมาน่ะ"
        },
        {
            "id": 24,
            "model": "동랑",
            "teller": "ทงรัง",
            "title": "แผนกพัฒนาทรัพยากรอาหารของ K คอร์ป",
            "content": "เหมือนจะเป็นของจากปีกที่ชื่อว่า K คอร์ป เห็นว่าเป็นกลุ่มของนาโนบอทขนาดกระจิดริดจนมองเผินๆ ก็จะเหมือนเป็นของเหลว และเมื่อนายฉีดมันเข้าไปนั้น..."
        },
        {
            "id": 25,
            "model": "동랑",
            "teller": "ทงรัง",
            "title": "แผนกพัฒนาทรัพยากรอาหารของ K คอร์ป",
            "content": "ไม่ว่านายจะถูกทุบ ถูกทำร้าย กระดูกหัก ถูกฉีก ถูกกระชาก หรือถูกสับจนเละแค่ไหน..."
        },
        {
            "id": 26,
            "model": "동랑",
            "teller": "ทงรัง",
            "title": "แผนกพัฒนาทรัพยากรอาหารของ K คอร์ป",
            "content": "มันก็จะฟื้นฟูกลับมาได้ในทันที สุดยอดไปเลยไม่ใช่รึไง? และไม่นานความเจ็บปวดก็จะหายไปด้วยเหมือนกัน ฮ่าฮ่าฮ่า"
        },
        {
            "id": 27,
            "model": "동랑",
            "teller": "ทงรัง",
            "title": "แผนกพัฒนาทรัพยากรอาหารของ K คอร์ป",
            "content": "เพราะงั้นแล้วมันไม่เป็นไรหรอกที่จะเจ็บปวด ฉันไม่ต้องดื้นรนทั้งกายและใจเพื่อรักษาอะไร ฉันมันโง่เอง ใช่ไหมล่ะ"
        },
        {
            "id": 28,
            "model": "이상",
            "content": "...ทงรัง"
        }
    ]
}